Workbook

Sheet 阶段交付物情况
A1: 文档 | H1: 适用组织 | K1: 文档颗粒度 | M1: 模板 | O1: 适用范围 | AC1: 备注
O2: 系统 | W2: 基础组件 | Z2: 实施组
A3: 序号 | B3: 模板编号 | C3: 项目阶段 | D3: 文档分类 | E3: 文件夹名称 | F3: 文档 | G3: 文档类型 | H3: 集团实施组 | I3: 联合办公实施组 | J3: 推广单位实施组 | K3: 共性（含板块）） | L3: 个性 | M3: 集团维度：[SPIC_JTTG]_[JTSSZ集团实施组]_[模块/独立标段]_[文档类型]_[文件名称]_[版本]_[日期].后缀 联合办公实施组维度：[SPIC_JTTG]_[综合清洁能源组]_[模块/独立标段]_[文档类型]_[文件名称]_[版本]_[日期].后缀 二级单位维度：[SPIC_JTTG]_[公司代码(A)][单位简称(B)]_[模块(C)]_[文档类型(D)]_[文件名称(E)]_[版本(F)]_[日期(G)].后缀 | N3: 牵头组 | O3: ERP | P3: 智能仓储 | Q3: 合同管理 | R3: 报销报账 | S3: 司库融合 | T3: 共享运营 | U3: 共享融合 | V3: 全面预算 | W3: MDG | X3: GRC | Y3: BPM | Z3: 集成技术 | AA3: 数据 | AB3: 项目群管理支撑 | AC3: 备注 | AD3: 是否有模板 | AE3: 已提交模板数量 | AF3: 编校审要求
A4: =ROW()-3 -> 1 | B4: 100 | C4: 01项目准备 | D4: 01项目管理类 | E4: 推广实施方案 | F4: 推广实施方案 | G4: PPT | H4: √ | I4: √ | J4: √ | M4: =_xlfn.TEXTJOIN("_",1,"SPIC_JTTG_XXXX_XXXX",D4,B4&F4,"V1.0_20260106") -> SPIC_JTTG_XXXX_XXXX_01项目管理类_100推广实施方案_V1.0_20260106 | N4: 项目群管理支撑 | AB4: √ | AD4: 是 | AE4: 1
A5: =ROW()-3 -> 2 | B5: 101 | C5: 01项目准备 | D5: 01项目管理类 | E5: 启动会材料 | F5: 启动会材料 | G5: PPT | H5: √ | I5: √ | J5: √ | M5: =_xlfn.TEXTJOIN("_",1,"SPIC_JTTG_XXXX_XXXX",D5,B5&F5,"V1.0_20260106") -> SPIC_JTTG_XXXX_XXXX_01项目管理类_101启动会材料_V1.0_20260106 | N5: 项目群管理支撑 | O5: √ | P5: √ | Q5: √ | R5: √ | S5: √ | T5: √ | U5: √ | V5: √ | W5: √ | X5: √ | Y5: √ | Z5: √ | AA5: √ | AB5: √ | AD5: 是 | AE5: 1
A6: =ROW()-3 -> 3 | B6: 102 | C6: 01项目准备 | D6: 01项目管理类 | E6: 计划管理 | F6: 项目里程碑计划 | G6: PPT | H6: √ | I6: √ | J6: √ | K6: 不涉及 | L6: 不涉及 | M6: =_xlfn.TEXTJOIN("_",1,"SPIC_JTTG_XXXX_XXXX",D6,B6&F6,"V1.0_20260106") -> SPIC_JTTG_XXXX_XXXX_01项目管理类_102项目里程碑计划_V1.0_20260106 | N6: 项目群管理支撑 | O6: × | P6: × | Q6: × | R6: × | S6: × | T6: × | U6: × | V6: × | W6: × | X6: × | Y6: × | Z6: × | AA6: × | AB6: √ | AD6: 否 | AE6: 0
A7: =ROW()-3 -> 4 | B7: 103 | C7: 01项目准备 | D7: 01项目管理类 | F7: 项目详细计划 | G7: Excel | H7: √ | I7: √ | J7: √ | M7: =_xlfn.TEXTJOIN("_",1,"SPIC_JTTG_XXXX_XXXX",D7,B7&F7,"V1.0_20260106") -> SPIC_JTTG_XXXX_XXXX_01项目管理类_103项目详细计划_V1.0_20260106 | N7: 项目群管理支撑 | O7: √ | P7: √ | Q7: √ | R7: √ | S7: √ | T7: √ | U7: √ | V7: √ | W7: √ | X7: √ | Y7: √ | Z7: √ | AA7: √ | AB7: √ | AD7: 是 | AE7: 1
A8: =ROW()-3 -> 5 | B8: 104 | C8: 01项目准备 | D8: 01项目管理类 | E8: 项目实施组组织架构 | F8: 项目实施组组织架构 | G8: PPT | H8: √ | I8: √ | J8: √ | M8: =_xlfn.TEXTJOIN("_",1,"SPIC_JTTG_XXXX_XXXX",D8,B8&F8,"V1.0_20260106") -> SPIC_JTTG_XXXX_XXXX_01项目管理类_104项目实施组组织架构_V1.0_20260106 | N8: 项目群管理支撑 | O8: × | P8: × | Q8: × | R8: × | S8: × | T8: × | U8: × | V8: × | W8: × | X8: × | Y8: × | Z8: × | AA8: × | AB8: √ | AD8: 是 | AE8: 1
A9: =ROW()-3 -> 6 | B9: 105 | C9: 01项目准备 | D9: 01项目管理类 | E9: 资源管理 | F9: 关键用户名单 | G9: Excel | H9: √ | I9: √ | J9: √ | M9: =_xlfn.TEXTJOIN("_",1,"SPIC_JTTG_XXXX_XXXX",D9,B9&F9,"V1.0_20260106") -> SPIC_JTTG_XXXX_XXXX_01项目管理类_105关键用户名单_V1.0_20260106 | N9: / | O9: √ | P9: √ | Q9: √ | R9: √ | S9: √ | T9: √ | U9: √ | V9: √ | W9: √ | X9: √ | Y9: √ | Z9: √ | AA9: √ | AD9: 是 | AE9: 1
A10: =ROW()-3 -> 7 | B10: 106 | C10: 01项目准备 | D10: 01项目管理类 | F10: 项目通讯录 | G10: Excel | H10: √ | I10: √ | J10: √ | K10: 不涉及 | L10: 不涉及 | M10: =_xlfn.TEXTJOIN("_",1,"SPIC_JTTG_XXXX_XXXX",D10,B10&F10,"V1.0_20260106") -> SPIC_JTTG_XXXX_XXXX_01项目管理类_106项目通讯录_V1.0_20260106 | N10: 项目群管理支撑 | O10: √ | P10: √ | Q10: √ | R10: √ | S10: √ | T10: √ | U10: √ | V10: √ | W10: √ | X10: √ | Y10: √ | Z10: √ | AA10: √ | AB10: √ | AD10: 是 | AE10: 1
A11: =ROW()-3 -> 8 | B11: 107 | C11: 01项目准备 | D11: 05人员培训类 | E11: 入场培训计划 | F11: 关键用户入场培训计划 | G11: Excel | H11: √ | J11: √ | M11: =_xlfn.TEXTJOIN("_",1,"SPIC_JTTG_XXXX_XXXX",D11,B11&F11,"V1.0_20260106") -> SPIC_JTTG_XXXX_XXXX_05人员培训类_107关键用户入场培训计划_V1.0_20260106 | N11: 项目群管理支撑 | O11: √ | P11: √ | Q11: √ | R11: √ | S11: √ | T11: √ | U11: √ | V11: √ | W11: √ | X11: √ | Y11: √ | Z11: √ | AA11: √ | AB11: √ | AD11: 是 | AE11: 1
A12: =ROW()-3 -> 9 | B12: 108 | C12: 01项目准备 | D12: 05人员培训类 | F12: 实施顾问入场培训计划 | G12: Excel | H12: √ | J12: √ | M12: =_xlfn.TEXTJOIN("_",1,"SPIC_JTTG_XXXX_XXXX",D12,B12&F12,"V1.0_20260106") -> SPIC_JTTG_XXXX_XXXX_05人员培训类_108实施顾问入场培训计划_V1.0_20260106 | N12: 项目群管理支撑 | O12: √ | P12: √ | Q12: √ | R12: √ | S12: √ | T12: √ | U12: √ | V12: √ | W12: √ | X12: √ | Y12: √ | Z12: √ | AA12: √ | AB12: √ | AD12: 是 | AE12: 1
A13: =ROW()-3 -> 10 | B13: 109 | C13: 01项目准备 | D13: 05人员培训类 | E13: 入场培训材料 | F13: 关键用户入场培训材料 | G13: PPT | H13: √ | J13: √ | K13: 不涉及 | L13: 不涉及 | M13: =_xlfn.TEXTJOIN("_",1,"SPIC_JTTG_XXXX_XXXX",D13,B13&F13,"V1.0_20260106") -> SPIC_JTTG_XXXX_XXXX_05人员培训类_109关键用户入场培训材料_V1.0_20260106 | N13: 项目群管理支撑 | O13: √ | P13: √ | Q13: √ | R13: √ | S13: √ | T13: √ | U13: √ | V13: √ | W13: √ | X13: √ | Y13: √ | Z13: √ | AA13: √ | AB13: √ | AD13: 是 | AE13: 1
A14: =ROW()-3 -> 11 | B14: 110 | C14: 01项目准备 | D14: 05人员培训类 | F14: 实施顾问入场培训材料 | G14: PPT,Word,Mp4 | H14: √ | J14: √ | M14: =_xlfn.TEXTJOIN("_",1,"SPIC_JTTG_XXXX_XXXX",D14,B14&F14,"V1.0_20260106") -> SPIC_JTTG_XXXX_XXXX_05人员培训类_110实施顾问入场培训材料_V1.0_20260106 | N14: 项目群管理支撑 | O14: √ | P14: √ | Q14: √ | R14: √ | S14: √ | T14: √ | U14: √ | V14: √ | W14: √ | X14: √ | Y14: √ | Z14: √ | AA14: √ | AB14: √ | AD14: 是 | AE14: 1
A15: =ROW()-3 -> 12 | B15: 111 | C15: 01项目准备 | D15: 05人员培训类 | E15: 入场培训签到表 | F15: 入场培训签到表 | G15: Word | H15: √ | J15: √ | M15: =_xlfn.TEXTJOIN("_",1,"SPIC_JTTG_XXXX_XXXX",D15,B15&F15,"V1.0_20260106") -> SPIC_JTTG_XXXX_XXXX_05人员培训类_111入场培训签到表_V1.0_20260106 | N15: 项目群管理支撑 | O15: √ | P15: √ | Q15: √ | R15: √ | S15: √ | T15: √ | U15: √ | V15: √ | W15: √ | X15: √ | Y15: √ | Z15: √ | AA15: √ | AB15: × | AD15: 是 | AE15: 1
A16: =ROW()-3 -> 13 | B16: 200 | C16: 02蓝图及详细方案迭代 | D16: 02系统实施类 | E16: 总体共性需求清单 | F16: 总体共性需求清单 | G16: Excel | H16: √ | M16: =_xlfn.TEXTJOIN("_",1,"SPIC_JTTG_XXXX_XXXX",D16,B16&F16,"V1.0_20260106") -> SPIC_JTTG_XXXX_XXXX_02系统实施类_200总体共性需求清单_V1.0_20260106 | N16: 项目群管理支撑 | O16: √ | P16: √ | Q16: √ | R16: √ | S16: √ | T16: √ | U16: √ | V16: √ | W16: √ | X16: √ | Y16: √ | Z16: × | AB16: × | AD16: 是 | AE16: 1 | AF16: 按需 | AG16: 已有签字
A17: =ROW()-3 -> 14 | B17: 201 | C17: 02蓝图及详细方案迭代 | D17: 02系统实施类 | E17: 集团实施组差异分析报告 | F17: 集团实施组差异分析报告 | G17: Word | H17: √ | M17: =_xlfn.TEXTJOIN("_",1,"SPIC_JTTG_XXXX_XXXX",D17,B17&F17,"V1.0_20260106") -> SPIC_JTTG_XXXX_XXXX_02系统实施类_201集团实施组差异分析报告_V1.0_20260106 | N17: 项目群管理支撑 | O17: √ | P17: √ | Q17: √ | R17: √ | S17: √ | T17: √ | U17: √ | V17: √ | W17: √ | X17: √ | Y17: √ | AB17: × | AD17: 是 | AE17: 1 | AF17: 按需 | AG17: 已有签字
A18: =ROW()-3 -> 15 | B18: 202 | C18: 02蓝图及详细方案迭代 | D18: 02系统实施类 | E18: 集团实施组蓝图及详细设计方案 | F18: 集团实施组蓝图及详细设计方案 | G18: PPT | H18: √ | M18: =_xlfn.TEXTJOIN("_",1,"SPIC_JTTG_XXXX_XXXX",D18,B18&F18,"V1.0_20260106") -> SPIC_JTTG_XXXX_XXXX_02系统实施类_202集团实施组蓝图及详细设计方案_V1.0_20260106 | N18: 项目群管理支撑 | O18: √ | P18: √ | Q18: √ | R18: √ | S18: √ | T18: √ | U18: √ | V18: √ | W18: √ | X18: √ | Y18: √ | AB18: × | AD18: 是 | AE18: 2 | AF18: 必需
A19: =ROW()-3 -> 16 | B19: 203 | C19: 02蓝图及详细方案迭代 | D19: 02系统实施类 | E19: 集团实施组流程图 | F19: 集团实施组流程图 | G19: Visio,Excel | H19: √ | M19: =_xlfn.TEXTJOIN("_",1,"SPIC_JTTG_XXXX_XXXX",D19,B19&F19,"V1.0_20260106") -> SPIC_JTTG_XXXX_XXXX_02系统实施类_203集团实施组流程图_V1.0_20260106 | N19: 项目群管理支撑 | O19: √ | P19: √ | Q19: √ | R19: √ | S19: √ | T19: √ | U19: √ | V19: √ | W19: √ | X19: √ | Y19: √ | Z19: × | AB19: × | AD19: 是 | AE19: 2 | AF19: - | AG19: 流程图已经含在蓝图材料和详设方案中
A20: =ROW()-3 -> 17 | B20: 204 | C20: 02蓝图及详细方案迭代 | D20: 02系统实施类 | E20: 集团实施组专题方案 | F20: 集团实施组专题方案 | G20: PPT | H20: √ | M20: =_xlfn.TEXTJOIN("_",1,"SPIC_JTTG_XXXX_XXXX",D20,B20&F20,"V1.0_20260106") -> SPIC_JTTG_XXXX_XXXX_02系统实施类_204集团实施组专题方案_V1.0_20260106 | N20: 项目群管理支撑 | O20: √ | P20: √ | Q20: √ | R20: √ | S20: √ | T20: √ | U20: √ | V20: √ | W20: √ | X20: √ | Y20: √ | AB20: × | AD20: 是 | AE20: 1 | AF20: 必需
A21: =ROW()-3 -> 18 | B21: 205 | C21: 02蓝图及详细方案迭代 | D21: 02系统实施类 | E21: 统建系统集成方案 | F21: 统建系统集成方案 | G21: PPT | H21: √ | M21: =_xlfn.TEXTJOIN("_",1,"SPIC_JTTG_XXXX_XXXX",D21,B21&F21,"V1.0_20260106") -> SPIC_JTTG_XXXX_XXXX_02系统实施类_205统建系统集成方案_V1.0_20260106 | N21: 集成组 | O21: × | P21: × | Q21: × | R21: × | S21: × | T21: × | U21: × | V21: × | W21: × | X21: × | Y21: × | Z21: √ | AB21: × | AD21: 是 | AE21: 1 | AF21: 必需
A22: =ROW()-3 -> 19 | B22: 206 | C22: 02蓝图及详细方案迭代 | D22: 02系统实施类 | E22: 业态共性需求清单 | F22: 业态共性需求清单 | G22: Excel | H22: × | I22: √ | M22: =_xlfn.TEXTJOIN("_",1,"SPIC_JTTG_XXXX_XXXX",D22,B22&F22,"V1.0_20260106") -> SPIC_JTTG_XXXX_XXXX_02系统实施类_206业态共性需求清单_V1.0_20260106 | N22: 项目群管理支撑 | O22: √ | P22: √ | Q22: √ | R22: √ | S22: √ | T22: √ | U22: √ | V22: √ | W22: √ | X22: √ | Y22: √ | AB22: × | AD22: 是 | AE22: 1 | AF22: 按需 | AG22: 已有签字件
A23: =ROW()-3 -> 20 | B23: 207 | C23: 02蓝图及详细方案迭代 | D23: 02系统实施类 | E23: 业态差异分析报告 | F23: 业态差异分析报告 | G23: Word | H23: × | I23: √ | M23: =_xlfn.TEXTJOIN("_",1,"SPIC_JTTG_XXXX_XXXX",D23,B23&F23,"V1.0_20260106") -> SPIC_JTTG_XXXX_XXXX_02系统实施类_207业态差异分析报告_V1.0_20260106 | N23: 项目群管理支撑 | O23: √ | P23: √ | Q23: √ | R23: √ | S23: √ | T23: √ | U23: √ | V23: √ | W23: √ | X23: √ | Y23: √ | AB23: × | AD23: 是 | AE23: 1 | AF23: 按需 | AG23: 已有签字件
A24: =ROW()-3 -> 21 | B24: 208 | C24: 02蓝图及详细方案迭代 | D24: 02系统实施类 | E24: 业态蓝图及详细设计方案 | F24: 业态蓝图及详细设计方案 | G24: PPT | H24: × | I24: √ | M24: =_xlfn.TEXTJOIN("_",1,"SPIC_JTTG_XXXX_XXXX",D24,B24&F24,"V1.0_20260106") -> SPIC_JTTG_XXXX_XXXX_02系统实施类_208业态蓝图及详细设计方案_V1.0_20260106 | N24: 项目群管理支撑 | O24: √ | P24: √ | Q24: √ | R24: √ | S24: √ | T24: √ | U24: √ | V24: √ | W24: √ | X24: √ | Y24: √ | AB24: × | AD24: 是 | AE24: 2 | AF24: 必需
A25: =ROW()-3 -> 22 | B25: 209 | C25: 02蓝图及详细方案迭代 | D25: 02系统实施类 | E25: 业态流程图 | F25: 业态流程图 | G25: Visio,Excel | H25: × | I25: √ | M25: =_xlfn.TEXTJOIN("_",1,"SPIC_JTTG_XXXX_XXXX",D25,B25&F25,"V1.0_20260106") -> SPIC_JTTG_XXXX_XXXX_02系统实施类_209业态流程图_V1.0_20260106 | N25: 项目群管理支撑 | O25: √ | P25: √ | Q25: √ | R25: √ | S25: √ | T25: √ | U25: √ | V25: √ | W25: √ | X25: √ | Y25: √ | AB25: × | AD25: 是 | AE25: 2 | AF25: - | AG25: 流程图已经含在蓝图材料和详设方案中
A26: =ROW()-3 -> 23 | B26: 210 | C26: 02蓝图及详细方案迭代 | D26: 02系统实施类 | E26: 业态专题方案（境外/核能/工程服务/金融专题方案） | F26: 业态专题方案（境外/核能/工程服务/金融专题方案） | G26: PPT | H26: × | I26: √ | M26: =_xlfn.TEXTJOIN("_",1,"SPIC_JTTG_XXXX_XXXX",D26,B26&F26,"V1.0_20260106") -> SPIC_JTTG_XXXX_XXXX_02系统实施类_210业态专题方案（境外/核能/工程服务/金融专题方案）_V1.0_20260106 | N26: 项目群管理支撑 | O26: √ | P26: √ | Q26: √ | R26: √ | S26: √ | T26: √ | U26: √ | V26: √ | W26: √ | X26: √ | Y26: √ | AB26: × | AD26: 是 | AE26: 1 | AF26: 必需
A27: =ROW()-3 -> 24 | B27: 211 | C27: 02蓝图及详细方案迭代 | D27: 02系统实施类 | E27: 个性需求清单 | F27: 个性需求清单 | G27: Excel | H27: × | J27: √ | M27: =_xlfn.TEXTJOIN("_",1,"SPIC_JTTG_XXXX_XXXX",D27,B27&F27,"V1.0_20260106") -> SPIC_JTTG_XXXX_XXXX_02系统实施类_211个性需求清单_V1.0_20260106 | N27: 项目群管理支撑 | O27: √ | P27: √ | Q27: √ | R27: √ | S27: √ | T27: √ | U27: √ | V27: √ | W27: √ | X27: √ | Y27: √ | AB27: × | AD27: 是 | AE27: 1 | AF27: 按需 | AG27: 已有签字件
A28: =ROW()-3 -> 25 | B28: 212 | C28: 02蓝图及详细方案迭代 | D28: 02系统实施类 | E28: 二级单位差异分析报告 | F28: 二级单位差异分析报告 | G28: Word | H28: × | J28: √ | M28: =_xlfn.TEXTJOIN("_",1,"SPIC_JTTG_XXXX_XXXX",D28,B28&F28,"V1.0_20260106") -> SPIC_JTTG_XXXX_XXXX_02系统实施类_212二级单位差异分析报告_V1.0_20260106 | N28: 项目群管理支撑 | O28: √ | P28: √ | Q28: √ | R28: √ | S28: √ | T28: √ | U28: √ | V28: √ | W28: √ | X28: √ | Y28: √ | AB28: × | AD28: 是 | AE28: 1 | AF28: 按需 | AG28: 已有签字件
A29: =ROW()-3 -> 26 | B29: 213 | C29: 02蓝图及详细方案迭代 | D29: 02系统实施类 | E29: 二级单位蓝图及详细设计方案 | F29: 二级单位蓝图及详细设计方案 | G29: PPT | H29: × | J29: √ | M29: =_xlfn.TEXTJOIN("_",1,"SPIC_JTTG_XXXX_XXXX",D29,B29&F29,"V1.0_20260106") -> SPIC_JTTG_XXXX_XXXX_02系统实施类_213二级单位蓝图及详细设计方案_V1.0_20260106 | N29: 项目群管理支撑 | O29: √ | P29: √ | Q29: √ | R29: √ | S29: √ | T29: √ | U29: √ | V29: √ | W29: √ | X29: √ | Y29: √ | AB29: × | AD29: 是 | AE29: 2 | AF29: 必需
A30: =ROW()-3 -> 27 | B30: 214 | C30: 02蓝图及详细方案迭代 | D30: 02系统实施类 | E30: 二级单位流程图 | F30: 二级单位流程图 | G30: Visio,Excel | H30: × | J30: √ | M30: =_xlfn.TEXTJOIN("_",1,"SPIC_JTTG_XXXX_XXXX",D30,B30&F30,"V1.0_20260106") -> SPIC_JTTG_XXXX_XXXX_02系统实施类_214二级单位流程图_V1.0_20260106 | N30: 项目群管理支撑 | O30: √ | P30: √ | Q30: √ | R30: √ | S30: √ | T30: √ | U30: √ | V30: √ | W30: √ | X30: √ | Y30: √ | AB30: × | AD30: 是 | AE30: 2 | AF30: - | AG30: 流程图已经含在蓝图材料和详设方案中
A31: =ROW()-3 -> 28 | B31: 215 | C31: 02蓝图及详细方案迭代 | D31: 02系统实施类 | E31: 二级单位专题方案 | F31: 二级单位专题方案 | G31: PPT | H31: × | J31: √ | M31: =_xlfn.TEXTJOIN("_",1,"SPIC_JTTG_XXXX_XXXX",D31,B31&F31,"V1.0_20260106") -> SPIC_JTTG_XXXX_XXXX_02系统实施类_215二级单位专题方案_V1.0_20260106 | N31: 项目群管理支撑 | O31: √ | P31: √ | Q31: √ | R31: √ | S31: √ | T31: √ | U31: √ | V31: √ | W31: √ | X31: √ | Y31: √ | Z31: × | AB31: × | AD31: 是 | AE31: 1 | AF31: 必需
A32: =ROW()-3 -> 29 | B32: 216 | C32: 02蓝图及详细方案迭代 | D32: 02系统实施类 | E32: 自建系统集成方案 | F32: 自建系统集成方案 | G32: PPT | H32: √ | M32: =_xlfn.TEXTJOIN("_",1,"SPIC_JTTG_XXXX_XXXX",D32,B32&F32,"V1.0_20260106") -> SPIC_JTTG_XXXX_XXXX_02系统实施类_216自建系统集成方案_V1.0_20260106 | N32: 集成管理 | O32: × | P32: × | Q32: × | R32: × | S32: × | T32: × | U32: × | V32: × | W32: × | X32: × | Y32: × | Z32: √ | AB32: × | AD32: 是 | AE32: 1 | AF32: 必需
A33: =ROW()-3 -> 30 | B33: 217 | C33: 02蓝图及详细方案迭代 | D33: 02系统实施类 | E33: 静态数据收集方案 | F33: 静态数据收集方案 | G33: Word,PPT | H33: √ | M33: =_xlfn.TEXTJOIN("_",1,"SPIC_JTTG_XXXX_XXXX",D33,B33&F33,"V1.0_20260106") -> SPIC_JTTG_XXXX_XXXX_02系统实施类_217静态数据收集方案_V1.0_20260106 | N33: 数据管理 | O33: × | P33: × | Q33: × | R33: × | S33: × | T33: × | U33: × | V33: × | W33: × | X33: × | Y33: × | Z33: × | AA33: √ | AB33: × | AD33: 是 | AE33: 2 | AF33: 必需
A34: =ROW()-3 -> 31 | B34: 218 | C34: 02蓝图及详细方案迭代 | D34: 04数据管理类 | E34: 静态数据收集计划及模板 | F34: 静态数据收集计划及模板 | G34: Excel | H34: √ | M34: =_xlfn.TEXTJOIN("_",1,"SPIC_JTTG_XXXX_XXXX",D34,B34&F34,"V1.0_20260106") -> SPIC_JTTG_XXXX_XXXX_04数据管理类_218静态数据收集计划及模板_V1.0_20260106 | N34: 数据管理 | O34: √ | P34: √ | Q34: √ | R34: √ | S34: √ | T34: √ | U34: √ | V34: √ | W34: √ | X34: √ | Y34: √ | Z34: × | AA34: √ | AB34: × | AC34: 缺少数据模板 | AD34: 是 | AE34: 1 | AF34: -
A35: =ROW()-3 -> 32 | B35: 219 | C35: 02蓝图及详细方案迭代 | D35: 02系统实施类 | E35: 详细设计方案评审汇报材料 | F35: 详细设计方案评审汇报材料 | G35: PPT | H35: √ | I35: √ | J35: √ | M35: =_xlfn.TEXTJOIN("_",1,"SPIC_JTTG_XXXX_XXXX",D35,B35&F35,"V1.0_20260106") -> SPIC_JTTG_XXXX_XXXX_02系统实施类_219详细设计方案评审汇报材料_V1.0_20260106 | N35: 项目群管理支撑 | O35: √ | P35: √ | Q35: √ | R35: √ | S35: √ | T35: √ | U35: √ | V35: √ | W35: √ | X35: √ | Y35: √ | AB35: × | AD35: 是 | AE35: 1 | AF35: 必需
A36: =ROW()-3 -> 33 | B36: 220 | C36: 02蓝图及详细方案迭代 | D36: 01项目管理类 | E36: 评审意见单 | F36: 评审意见单 | G36: Word | H36: √ | I36: √ | J36: √ | M36: =_xlfn.TEXTJOIN("_",1,"SPIC_JTTG_XXXX_XXXX",D36,B36&F36,"V1.0_20260106") -> SPIC_JTTG_XXXX_XXXX_01项目管理类_220评审意见单_V1.0_20260106 | N36: 项目群管理支撑 | O36: √ | P36: √ | Q36: √ | R36: √ | S36: √ | T36: √ | U36: √ | V36: √ | W36: √ | X36: √ | Y36: √ | AB36: × | AD36: 是 | AE36: 1 | AF36: - | AG36: 签字件
A37: =ROW()-3 -> 34 | B37: 221 | C37: 02蓝图及详细方案迭代 | D37: 03技术管理类 | E37: 开发清单 | F37: 开发清单 | G37: Excel | H37: √ | I37: √ | J37: √ | M37: =_xlfn.TEXTJOIN("_",1,"SPIC_JTTG_XXXX_XXXX",D37,B37&F37,"V1.0_20260106") -> SPIC_JTTG_XXXX_XXXX_03技术管理类_221开发清单_V1.0_20260106 | N37: 集成技术 | O37: √ | P37: √ | Q37: √ | R37: √ | S37: √ | T37: √ | U37: √ | V37: √ | W37: √ | X37: √ | Y37: √ | Z37: √ | AA37: × | AD37: 是 | AE37: 1 | AF37: 必需
A38: =ROW()-3 -> 35 | B38: 222 | C38: 02蓝图及详细方案迭代 | D38: 03技术管理类 | E38: 集成清单 | F38: 集成清单 | G38: Excel | H38: √ | I38: √ | J38: √ | M38: =_xlfn.TEXTJOIN("_",1,"SPIC_JTTG_XXXX_XXXX",D38,B38&F38,"V1.0_20260106") -> SPIC_JTTG_XXXX_XXXX_03技术管理类_222集成清单_V1.0_20260106 | N38: 集成管理 | O38: √ | P38: √ | Q38: √ | R38: √ | S38: √ | T38: √ | U38: √ | V38: √ | W38: √ | X38: √ | Y38: √ | Z38: √ | AD38: 是 | AE38: 1 | AF38: 必需
A39: =ROW()-3 -> 36 | B39: 300 | C39: 03系统实现 | D39: 03技术管理类 | E39: 共性功能设计说明书 | F39: 共性功能设计说明书 | G39: Word | H39: √ | I39: √ | M39: =_xlfn.TEXTJOIN("_",1,"SPIC_JTTG_XXXX_XXXX",D39,B39&F39,"V1.0_20260106") -> SPIC_JTTG_XXXX_XXXX_03技术管理类_300共性功能设计说明书_V1.0_20260106 | N39: 项目群管理支撑 | O39: √ | P39: √ | Q39: √ | R39: √ | S39: √ | T39: √ | U39: √ | V39: √ | W39: √ | X39: √ | Y39: √ | Z39: × | AA39: × | AB39: × | AD39: 是 | AE39: 1 | AF39: 必需
A40: =ROW()-3 -> 37 | B40: 301 | C40: 03系统实现 | D40: 03技术管理类 | E40: 共性技术功能设计说明书 | F40: 共性技术功能设计说明书 | G40: Word | H40: √ | I40: √ | M40: =_xlfn.TEXTJOIN("_",1,"SPIC_JTTG_XXXX_XXXX",D40,B40&F40,"V1.0_20260106") -> SPIC_JTTG_XXXX_XXXX_03技术管理类_301共性技术功能设计说明书_V1.0_20260106 | N40: 项目群管理支撑 | O40: √ | P40: √ | Q40: √ | R40: √ | S40: √ | T40: √ | U40: √ | V40: √ | W40: √ | X40: √ | Y40: √ | AB40: × | AD40: 是 | AE40: 1 | AF40: 必需
A41: =ROW()-3 -> 38 | B41: 302 | C41: 03系统实现 | D41: 02系统实施类 | E41: 集团实施组单元测试计划及场景 | F41: 集团实施组单元测试计划及场景 | G41: Excel | H41: √ | M41: =_xlfn.TEXTJOIN("_",1,"SPIC_JTTG_XXXX_XXXX",D41,B41&F41,"V1.0_20260106") -> SPIC_JTTG_XXXX_XXXX_02系统实施类_302集团实施组单元测试计划及场景_V1.0_20260106 | N41: / | O41: √ | P41: √ | Q41: √ | R41: √ | S41: √ | T41: √ | U41: √ | V41: √ | W41: √ | X41: √ | Y41: √ | AD41: 是 | AE41: 1 | AF41: 按需 | AG41: 集团实施组必须要求
A42: =ROW()-3 -> 39 | B42: 303 | C42: 03系统实现 | D42: 02系统实施类 | E42: 集团实施组单元测试报告 | F42: 集团实施组单元测试报告 | G42: Word | H42: √ | M42: =_xlfn.TEXTJOIN("_",1,"SPIC_JTTG_XXXX_XXXX",D42,B42&F42,"V1.0_20260106") -> SPIC_JTTG_XXXX_XXXX_02系统实施类_303集团实施组单元测试报告_V1.0_20260106 | N42: / | O42: √ | P42: √ | Q42: √ | R42: √ | S42: √ | T42: √ | U42: √ | V42: √ | W42: √ | X42: √ | Y42: √ | AD42: 是 | AE42: 1 | AF42: - | AG42: 已要求签字
A43: =ROW()-3 -> 40 | B43: 304 | C43: 03系统实现 | D43: 02系统实施类 | E43: 集团实施组集成测试计划及场景 | F43: 集团实施组集成测试计划及场景 | G43: Excel | H43: √ | M43: =_xlfn.TEXTJOIN("_",1,"SPIC_JTTG_XXXX_XXXX",D43,B43&F43,"V1.0_20260106") -> SPIC_JTTG_XXXX_XXXX_02系统实施类_304集团实施组集成测试计划及场景_V1.0_20260106 | N43: 项目群管理支撑 | O43: √ | P43: √ | Q43: √ | R43: √ | S43: √ | T43: √ | U43: √ | V43: √ | W43: √ | X43: √ | Y43: √ | AD43: 是 | AE43: 1 | AF43: 按需 | AG43: 集团实施组必须要求
A44: =ROW()-3 -> 41 | B44: 305 | C44: 03系统实现 | D44: 02系统实施类 | E44: 集团实施组集成测试报告 | F44: 集团实施组集成测试报告 | G44: Word | H44: √ | M44: =_xlfn.TEXTJOIN("_",1,"SPIC_JTTG_XXXX_XXXX",D44,B44&F44,"V1.0_20260106") -> SPIC_JTTG_XXXX_XXXX_02系统实施类_305集团实施组集成测试报告_V1.0_20260106 | N44: / | O44: √ | P44: √ | Q44: √ | R44: √ | S44: √ | T44: √ | U44: √ | V44: √ | W44: √ | X44: √ | Y44: √ | AD44: 是 | AE44: 1 | AF44: - | AG44: 已要求签字
A45: =ROW()-3 -> 42 | B45: 306 | C45: 03系统实现 | D45: 03技术管理类 | E45: 配置清单 | F45: 配置清单 | G45: Excel | H45: √ | I45: × | J45: √ | M45: =_xlfn.TEXTJOIN("_",1,"SPIC_JTTG_XXXX_XXXX",D45,B45&F45,"V1.0_20260106") -> SPIC_JTTG_XXXX_XXXX_03技术管理类_306配置清单_V1.0_20260106 | N45: 项目群管理支撑 | O45: √ | X45: √ | AB45: × | AC45: 建议区分标准配置、个性化配置 | AD45: 是 | AE45: 1 | AF45: - | AG45: 已要求签字
A46: =ROW()-3 -> 43 | B46: 307 | C46: 03系统实现 | D46: 03技术管理类 | E46: 个性功能设计说明书 | F46: 个性功能设计说明书 | G46: Word | H46: × | I46: × | J46: √ | M46: =_xlfn.TEXTJOIN("_",1,"SPIC_JTTG_XXXX_XXXX",D46,B46&F46,"V1.0_20260106") -> SPIC_JTTG_XXXX_XXXX_03技术管理类_307个性功能设计说明书_V1.0_20260106 | N46: 项目群管理支撑 | O46: √ | P46: √ | Q46: √ | R46: √ | S46: √ | T46: √ | U46: √ | V46: √ | W46: √ | X46: √ | Y46: √ | Z46: × | AA46: × | AB46: × | AD46: 是 | AE46: 1 | AF46: 按需
A47: =ROW()-3 -> 44 | B47: 308 | C47: 03系统实现 | D47: 03技术管理类 | E47: 个性功能技术设计说明书 | F47: 个性功能技术设计说明书 | G47: Word | H47: × | I47: × | J47: √ | M47: =_xlfn.TEXTJOIN("_",1,"SPIC_JTTG_XXXX_XXXX",D47,B47&F47,"V1.0_20260106") -> SPIC_JTTG_XXXX_XXXX_03技术管理类_308个性功能技术设计说明书_V1.0_20260106 | N47: 项目群管理支撑 | O47: √ | P47: √ | Q47: √ | R47: √ | S47: √ | T47: √ | U47: √ | V47: √ | W47: √ | X47: √ | Y47: √ | Z47: × | AA47: × | AB47: × | AD47: 是 | AE47: 1 | AF47: 按需
A48: =ROW()-3 -> 45 | B48: 309 | C48: 03系统实现 | D48: 02系统实施类 | E48: 二级单位单元测试计划及场景 | F48: 二级单位单元测试计划及场景 | G48: Excel | H48: × | I48: × | J48: √ | M48: =_xlfn.TEXTJOIN("_",1,"SPIC_JTTG_XXXX_XXXX",D48,B48&F48,"V1.0_20260106") -> SPIC_JTTG_XXXX_XXXX_02系统实施类_309二级单位单元测试计划及场景_V1.0_20260106 | O48: √ | P48: √ | Q48: √ | R48: √ | S48: √ | T48: √ | U48: √ | V48: √ | W48: √ | X48: √ | Y48: √ | AD48: 是 | AE48: 1 | AF48: 按需
A49: =ROW()-3 -> 46 | B49: 310 | C49: 03系统实现 | D49: 02系统实施类 | E49: 二级单位单元测试报告 | F49: 二级单位单元测试报告 | G49: Word | H49: × | I49: × | J49: √ | M49: =_xlfn.TEXTJOIN("_",1,"SPIC_JTTG_XXXX_XXXX",D49,B49&F49,"V1.0_20260106") -> SPIC_JTTG_XXXX_XXXX_02系统实施类_310二级单位单元测试报告_V1.0_20260106 | O49: √ | P49: √ | Q49: √ | R49: √ | S49: √ | T49: √ | U49: √ | V49: √ | W49: √ | X49: √ | Y49: √ | AD49: 是 | AE49: 1 | AF49: - | AG49: 已要求签字
A50: =ROW()-3 -> 47 | B50: 311 | C50: 03系统实现 | D50: 02系统实施类 | E50: 二级单位集成测试计划及场景 | F50: 二级单位集成测试计划及场景 | G50: Excel | H50: × | I50: × | J50: √ | M50: =_xlfn.TEXTJOIN("_",1,"SPIC_JTTG_XXXX_XXXX",D50,B50&F50,"V1.0_20260106") -> SPIC_JTTG_XXXX_XXXX_02系统实施类_311二级单位集成测试计划及场景_V1.0_20260106 | O50: √ | P50: √ | Q50: √ | R50: √ | S50: √ | T50: √ | U50: √ | V50: √ | W50: √ | X50: √ | Y50: √ | AD50: 是 | AE50: 1 | AF50: 按需
A51: =ROW()-3 -> 48 | B51: 312 | C51: 03系统实现 | D51: 02系统实施类 | E51: 二级单位集成测试报告 | F51: 二级单位集成测试报告 | G51: Word | H51: × | I51: × | J51: √ | M51: =_xlfn.TEXTJOIN("_",1,"SPIC_JTTG_XXXX_XXXX",D51,B51&F51,"V1.0_20260106") -> SPIC_JTTG_XXXX_XXXX_02系统实施类_312二级单位集成测试报告_V1.0_20260106 | O51: √ | P51: √ | Q51: √ | R51: √ | S51: √ | T51: √ | U51: √ | V51: √ | W51: √ | X51: √ | Y51: √ | AD51: 是 | AE51: 1 | AF51: - | AG51: 已要求签字
A52: =ROW()-3 -> 49 | B52: 313 | C52: 03系统实现 | D52: 03技术管理类 | E52: 权限角色收集模板 | F52: 权限角色收集模板 | G52: Excel,Word | H52: √ | I52: × | J52: × | M52: =_xlfn.TEXTJOIN("_",1,"SPIC_JTTG_XXXX_XXXX",D52,B52&F52,"V1.0_20260106") -> SPIC_JTTG_XXXX_XXXX_03技术管理类_313权限角色收集模板_V1.0_20260106 | N52: GRC | O52: × | P52: × | Q52: × | R52: × | S52: × | T52: × | U52: × | V52: × | W52: × | X52: √ | Y52: √ | Z52: × | AA52: × | AB52: × | AD52: 是 | AE52: 2 | AF52: -
A53: =ROW()-3 -> 50 | B53: 314 | C53: 03系统实现 | D53: 04数据管理类 | E53: 静态数据明细 | F53: 静态数据明细 | G53: Excel | H53: × | I53: × | J53: √ | M53: =_xlfn.TEXTJOIN("_",1,"SPIC_JTTG_XXXX_XXXX",D53,B53&F53,"V1.0_20260106") -> SPIC_JTTG_XXXX_XXXX_04数据管理类_314静态数据明细_V1.0_20260106 | N53: 数据管理 | O53: √ | P53: √ | Q53: √ | R53: √ | S53: √ | T53: √ | U53: √ | V53: √ | W53: √ | X53: √ | Y53: √ | Z53: × | AA53: √ | AB53: × | AC53: 参照218静态数据收集模板 | AD53: 否 | AE53: 不涉及 | AF53: - | AG53: 静态数据需要签字
A54: =ROW()-3 -> 51 | B54: 315 | C54: 03系统实现 | D54: 03技术管理类 | E54: BPM工作流收集模板 | F54: BPM工作流收集模板 | G54: Excel,Word | H54: √ | I54: × | J54: × | M54: =_xlfn.TEXTJOIN("_",1,"SPIC_JTTG_XXXX_XXXX",D54,B54&F54,"V1.0_20260106") -> SPIC_JTTG_XXXX_XXXX_03技术管理类_315BPM工作流收集模板_V1.0_20260106 | N54: BPM | O54: × | P54: × | Q54: × | R54: × | S54: × | T54: × | U54: × | V54: × | W54: × | X54: × | Y54: √ | Z54: × | AA54: × | AB54: × | AC54: 不同系统模板不同 | AD54: 是 | AE54: 2 | AF54: -
A55: =ROW()-3 -> 52 | B55: 400 | C55: 04上线准备及切换 | D55: 02系统实施类 | E55: 项目整体上线切换策略及方案 | F55: 项目整体上线切换策略及方案 | G55: Word,PPT | H55: √ | I55: × | J55: √ | M55: =_xlfn.TEXTJOIN("_",1,"SPIC_JTTG_XXXX_XXXX",D55,B55&F55,"V1.0_20260106") -> SPIC_JTTG_XXXX_XXXX_02系统实施类_400项目整体上线切换策略及方案_V1.0_20260106 | O55: √ | P55: √ | Q55: √ | R55: √ | S55: √ | T55: √ | U55: √ | V55: √ | W55: √ | X55: √ | Y55: √ | Z55: √ | AA55: √ | AC55: 2个 | AD55: 是 | AE55: 2 | AF55: 必需
A56: =ROW()-3 -> 53 | B56: 401 | C56: 04上线准备及切换 | D56: 01项目管理类 | E56: 共性问题清单 | F56: 共性问题清单 | G56: Excel | H56: √ | I56: √ | J56: × | M56: =_xlfn.TEXTJOIN("_",1,"SPIC_JTTG_XXXX_XXXX",D56,B56&F56,"V1.0_20260106") -> SPIC_JTTG_XXXX_XXXX_01项目管理类_401共性问题清单_V1.0_20260106 | N56: 项目群管理支撑 | O56: √ | P56: √ | Q56: √ | R56: √ | S56: √ | T56: √ | U56: √ | V56: √ | W56: √ | X56: √ | Y56: √ | Z56: √ | AA56: √ | AB56: √ | AD56: 是 | AE56: 1 | AF56: - | AG56: 在实施管理工具中统一管理
A57: =ROW()-3 -> 54 | B57: 402 | C57: 04上线准备及切换 | D57: 02系统实施类 | E57: 二级单位上线切换策略 | F57: 二级单位上线切换策略 | G57: Word | H57: × | I57: × | J57: √ | M57: =_xlfn.TEXTJOIN("_",1,"SPIC_JTTG_XXXX_XXXX",D57,B57&F57,"V1.0_20260106") -> SPIC_JTTG_XXXX_XXXX_02系统实施类_402二级单位上线切换策略_V1.0_20260106 | O57: √ | P57: √ | Q57: √ | R57: √ | S57: √ | T57: √ | U57: √ | V57: √ | W57: √ | X57: √ | Y57: √ | AD57: 是 | AE57: 1 | AF57: 按需
A58: =ROW()-3 -> 55 | B58: 403 | C58: 04上线准备及切换 | D58: 01项目管理类 | E58: 个性问题清单 | F58: 个性问题清单 | G58: Excel | H58: × | I58: × | J58: √ | M58: =_xlfn.TEXTJOIN("_",1,"SPIC_JTTG_XXXX_XXXX",D58,B58&F58,"V1.0_20260106") -> SPIC_JTTG_XXXX_XXXX_01项目管理类_403个性问题清单_V1.0_20260106 | O58: √ | P58: √ | Q58: √ | R58: √ | S58: √ | T58: √ | U58: √ | V58: √ | W58: √ | X58: √ | Y58: √ | AD58: 是 | AE58: 1 | AF58: -
A59: =ROW()-3 -> 56 | B59: 404 | C59: 04上线准备及切换 | D59: 02系统实施类 | E59: UAT测试计划及场景 | F59: UAT测试计划及场景 | G59: Excel | H59: √ | I59: × | J59: √ | M59: =_xlfn.TEXTJOIN("_",1,"SPIC_JTTG_XXXX_XXXX",D59,B59&F59,"V1.0_20260106") -> SPIC_JTTG_XXXX_XXXX_02系统实施类_404UAT测试计划及场景_V1.0_20260106 | N59: 项目群管理支撑 | O59: √ | P59: √ | Q59: √ | R59: √ | S59: √ | T59: √ | U59: √ | V59: √ | W59: √ | X59: √ | Y59: √ | AB59: × | AD59: 是 | AE59: 1 | AF59: 按需
A60: =ROW()-3 -> 57 | B60: 405 | C60: 04上线准备及切换 | D60: 02系统实施类 | E60: UAT测试报告 | F60: UAT测试报告 | G60: Word | H60: √ | I60: × | J60: √ | M60: =_xlfn.TEXTJOIN("_",1,"SPIC_JTTG_XXXX_XXXX",D60,B60&F60,"V1.0_20260106") -> SPIC_JTTG_XXXX_XXXX_02系统实施类_405UAT测试报告_V1.0_20260106 | N60: 项目群管理支撑 | O60: √ | P60: √ | Q60: √ | R60: √ | S60: √ | T60: √ | U60: √ | V60: √ | W60: √ | X60: √ | Y60: √ | AB60: × | AD60: 是 | AE60: 1 | AF60: - | AG60: 测试报告有签字
A61: =ROW()-3 -> 58 | B61: 406 | C61: 04上线准备及切换 | D61: 05人员培训类 | E61: 最终用户培训总结 | F61: 最终用户培训总结 | G61: Word | H61: √ | I61: × | J61: √ | M61: =_xlfn.TEXTJOIN("_",1,"SPIC_JTTG_XXXX_XXXX",D61,B61&F61,"V1.0_20260106") -> SPIC_JTTG_XXXX_XXXX_05人员培训类_406最终用户培训总结_V1.0_20260106 | O61: √ | P61: √ | Q61: √ | R61: √ | S61: √ | T61: √ | U61: √ | V61: √ | W61: √ | X61: √ | Y61: √ | AD61: 是 | AE61: 1 | AF61: 必需
A62: =ROW()-3 -> 59 | B62: 407 | C62: 04上线准备及切换 | D62: 01项目管理类 | E62: 最终用户账号及授权信息收集确认单 | F62: 最终用户账号及授权信息收集确认单 | G62: Excel,Word | H62: √ | I62: × | J62: √ | M62: =_xlfn.TEXTJOIN("_",1,"SPIC_JTTG_XXXX_XXXX",D62,B62&F62,"V1.0_20260106") -> SPIC_JTTG_XXXX_XXXX_01项目管理类_407最终用户账号及授权信息收集确认单_V1.0_20260106 | N62: GRC | O62: √ | P62: √ | Q62: √ | R62: √ | S62: √ | T62: √ | U62: √ | V62: √ | W62: √ | X62: √ | Y62: √ | AB62: × | AC62: 多个文件 | AD62: 是 | AE62: 5 | AF62: - | AG62: 已要求签字
A63: =ROW()-3 -> 60 | B63: 408 | C63: 04上线准备及切换 | D63: 04数据管理类 | E63: 静态、动态数据签署报告 | F63: 静态、动态数据签署报告 | G63: Word | H63: √ | I63: × | J63: √ | M63: =_xlfn.TEXTJOIN("_",1,"SPIC_JTTG_XXXX_XXXX",D63,B63&F63,"V1.0_20260106") -> SPIC_JTTG_XXXX_XXXX_04数据管理类_408静态、动态数据签署报告_V1.0_20260106 | N63: 数据管理 | O63: √ | P63: √ | Q63: √ | R63: √ | S63: √ | T63: √ | U63: √ | V63: √ | W63: √ | X63: √ | Y63: √ | AB63: × | AC63: 2个（静态、动态） | AD63: 是 | AE63: 2 | AF63: - | AG63: 已要求签字
A64: =ROW()-3 -> 61 | B64: 409 | C64: 04上线准备及切换 | D64: 01项目管理类 | E64: 上线开账准备及开账申请 | F64: 上线开账准备及开账申请 | G64: Word | J64: √ | M64: =_xlfn.TEXTJOIN("_",1,"SPIC_JTTG_XXXX_XXXX",D64,B64&F64,"V1.0_20260106") -> SPIC_JTTG_XXXX_XXXX_01项目管理类_409上线开账准备及开账申请_V1.0_20260106 | N64: 项目群管理支撑 | O64: × | P64: × | Q64: × | R64: × | S64: × | T64: × | U64: × | V64: × | W64: × | X64: × | Y64: × | Z64: × | AA64: × | AB64: √ | AD64: 是 | AE64: 2 | AF64: - | AG64: 已有签字
A65: =ROW()-3 -> 62 | B65: 410 | C65: 04上线准备及切换 | D65: 01项目管理类 | E65: 开账检查报告 | F65: 上线开账准备及开账申请检查评估报告 | G65: Word | H65: √ | M65: =_xlfn.TEXTJOIN("_",1,"SPIC_JTTG_XXXX_XXXX",D65,B65&F65,"V1.0_20260106") -> SPIC_JTTG_XXXX_XXXX_01项目管理类_410上线开账准备及开账申请检查评估报告_V1.0_20260106 | N65: 项目群管理支撑 | O65: × | P65: × | Q65: × | R65: × | S65: × | T65: × | U65: × | V65: × | W65: × | X65: × | Y65: × | Z65: × | AA65: × | AB65: √ | AD65: 是 | AE65: 1 | AF65: - | AG65: 已有签字
A66: =ROW()-3 -> 63 | B66: 411 | C66: 04上线准备及切换 | D66: 05人员培训类 | E66: 操作手册 | F66: 操作手册 | G66: Word | H66: √ | M66: =_xlfn.TEXTJOIN("_",1,"SPIC_JTTG_XXXX_XXXX",D66,B66&F66,"V1.0_20260106") -> SPIC_JTTG_XXXX_XXXX_05人员培训类_411操作手册_V1.0_20260106 | O66: √ | P66: √ | Q66: √ | R66: √ | S66: √ | T66: √ | U66: √ | V66: √ | W66: √ | X66: √ | Y66: √ | AD66: 是 | AE66: 1 | AF66: 按需 | AG66: 集团实施组必须要求
A67: =ROW()-3 -> 64 | B67: 412 | C67: 04上线准备及切换 | D67: 05人员培训类 | E67: 考试试卷 | F67: 考试试卷 | G67: Word | H67: √ | M67: =_xlfn.TEXTJOIN("_",1,"SPIC_JTTG_XXXX_XXXX",D67,B67&F67,"V1.0_20260106") -> SPIC_JTTG_XXXX_XXXX_05人员培训类_412考试试卷_V1.0_20260106 | O67: √ | P67: √ | Q67: √ | R67: √ | S67: √ | T67: √ | U67: √ | V67: √ | W67: √ | X67: √ | Y67: √ | AD67: 是 | AE67: 1 | AF67: -
A68: =ROW()-3 -> 65 | B68: 413 | C68: 04上线准备及切换 | D68: 05人员培训类 | E68: 培训录屏 | F68: 培训录屏 | G68: Mp4 | H68: √ | M68: =_xlfn.TEXTJOIN("_",1,"SPIC_JTTG_XXXX_XXXX",D68,B68&F68,"V1.0_20260106") -> SPIC_JTTG_XXXX_XXXX_05人员培训类_413培训录屏_V1.0_20260106 | O68: √ | P68: √ | Q68: √ | R68: √ | S68: √ | T68: √ | U68: √ | V68: √ | W68: √ | X68: √ | Y68: √ | AD68: 是 | AE68: 3 | AF68: -
A69: =ROW()-3 -> 66 | B69: 414 | C69: 04上线准备及切换 | D69: 03技术管理类 | E69: 性能测试方案 | F69: 性能测试方案 | G69: Word | H69: √ | M69: =_xlfn.TEXTJOIN("_",1,"SPIC_JTTG_XXXX_XXXX",D69,B69&F69,"V1.0_20260106") -> SPIC_JTTG_XXXX_XXXX_03技术管理类_414性能测试方案_V1.0_20260106 | O69: × | P69: × | Q69: × | R69: × | S69: × | T69: × | U69: × | V69: × | W69: × | X69: × | Y69: × | Z69: √ | AA69: × | AD69: 是 | AE69: 1 | AF69: 必需
A70: =ROW()-3 -> 67 | B70: 415 | C70: 04上线准备及切换 | D70: 03技术管理类 | E70: 性能测试报告 | F70: 性能测试报告 | G70: Word | H70: √ | M70: =_xlfn.TEXTJOIN("_",1,"SPIC_JTTG_XXXX_XXXX",D70,B70&F70,"V1.0_20260106") -> SPIC_JTTG_XXXX_XXXX_03技术管理类_415性能测试报告_V1.0_20260106 | O70: √ | P70: √ | Q70: √ | R70: √ | S70: √ | T70: √ | U70: √ | V70: √ | W70: √ | X70: √ | Y70: √ | Z70: √ | AB70: × | AC70: 第三方出报告 | AD70: 是 | AE70: 1 | AF70: - | AG70: 已有签字
A71: =ROW()-3 -> 68 | B71: 416 | C71: 04上线准备及切换 | D71: 03技术管理类 | E71: 系统应急预案 | F71: 系统应急预案 | G71: Word | H71: √ | J71: √ | M71: =_xlfn.TEXTJOIN("_",1,"SPIC_JTTG_XXXX_XXXX",D71,B71&F71,"V1.0_20260106") -> SPIC_JTTG_XXXX_XXXX_03技术管理类_416系统应急预案_V1.0_20260106 | O71: √ | P71: √ | Q71: √ | R71: √ | S71: √ | T71: √ | U71: √ | V71: √ | W71: √ | X71: √ | Y71: √ | Z71: √ | AA71: √ | AB71: × | AD71: 是 | AE71: 1 | AF71: 必需
A72: =ROW()-3 -> 69 | B72: 417 | C72: 04上线准备及切换 | D72: 04数据管理类 | E72: 数据备份及恢复方案 | F72: 数据备份及恢复方案 | G72: Word | H72: √ | J72: √ | M72: =_xlfn.TEXTJOIN("_",1,"SPIC_JTTG_XXXX_XXXX",D72,B72&F72,"V1.0_20260106") -> SPIC_JTTG_XXXX_XXXX_04数据管理类_417数据备份及恢复方案_V1.0_20260106 | N72: 数据管理 | AA72: √ | AB72: × | AD72: 否 | AE72: 不涉及 | AF72: 必需
A73: =ROW()-3 -> 70 | B73: 500 | C73: 05上线试运行支持 | D73: 01项目管理类 | E73: 系统上线运行报告 | F73: 系统上线运行报告 | G73: Word | H73: √ | J73: √ | M73: =_xlfn.TEXTJOIN("_",1,"SPIC_JTTG_XXXX_XXXX",D73,B73&F73,"V1.0_20260106") -> SPIC_JTTG_XXXX_XXXX_01项目管理类_500系统上线运行报告_V1.0_20260106 | N73: 项目群管理支撑 | O73: √ | P73: √ | Q73: √ | R73: √ | S73: √ | T73: √ | U73: √ | V73: √ | W73: √ | X73: √ | Y73: √ | Z73: × | AA73: × | AB73: √ | AD73: 是 | AE73: 1 | AF73: - | AG73: 已有签字
A74: =ROW()-3 -> 71 | B74: 501 | C74: 05上线试运行支持 | D74: 01项目管理类 | E74: 上线质量报告 | F74: 上线质量报告 | G74: Word | H74: √ | I74: √ | J74: √ | M74: =_xlfn.TEXTJOIN("_",1,"SPIC_JTTG_XXXX_XXXX",D74,B74&F74,"V1.0_20260106") -> SPIC_JTTG_XXXX_XXXX_01项目管理类_501上线质量报告_V1.0_20260106 | N74: 项目群管理支撑 | O74: √ | P74: √ | Q74: √ | R74: √ | S74: √ | T74: √ | U74: √ | V74: √ | W74: √ | X74: √ | Y74: √ | Z74: × | AA74: × | AB74: √ | AD74: 是 | AE74: 1 | AF74: 待定
A75: =ROW()-3 -> 72 | B75: 502 | C75: 05上线试运行支持 | D75: 01项目管理类 | E75: 上线单位问题清单 | F75: 上线单位问题清单 | G75: Excel | H75: √ | I75: √ | J75: √ | M75: =_xlfn.TEXTJOIN("_",1,"SPIC_JTTG_XXXX_XXXX",D75,B75&F75,"V1.0_20260106") -> SPIC_JTTG_XXXX_XXXX_01项目管理类_502上线单位问题清单_V1.0_20260106 | N75: 项目群管理支撑 | O75: √ | P75: √ | Q75: √ | R75: √ | S75: √ | T75: √ | U75: √ | V75: √ | W75: √ | X75: √ | Y75: √ | Z75: × | AA75: × | AB75: √ | AD75: 是 | AE75: 1 | AF75: -
A76: =ROW()-3 -> 73 | B76: 503 | C76: 05上线试运行支持 | D76: 01项目管理类 | E76: 月结报告 | F76: 月结报告 | G76: Word | H76: √ | I76: × | J76: √ | M76: =_xlfn.TEXTJOIN("_",1,"SPIC_JTTG_XXXX_XXXX",D76,B76&F76,"V1.0_20260106") -> SPIC_JTTG_XXXX_XXXX_01项目管理类_503月结报告_V1.0_20260106 | N76: ERP-财务组 | P76: × | Q76: × | W76: × | X76: × | Y76: × | Z76: × | AA76: × | AB76: × | AD76: 是 | AE76: 1 | AF76: - | AG76: 已有签字
A77: =ROW()-3 -> 74 | B77: 600 | C77: 06项目验收 | D77: 01项目管理类 | E77: 项目文档验收报告 | F77: 项目文档验收报告 | G77: Word | H77: √ | I77: √ | J77: √ | M77: =_xlfn.TEXTJOIN("_",1,"SPIC_JTTG_XXXX_XXXX",D77,B77&F77,"V1.0_20260106") -> SPIC_JTTG_XXXX_XXXX_01项目管理类_600项目文档验收报告_V1.0_20260106 | N77: 项目群管理支撑 | O77: √ | P77: √ | Q77: √ | R77: √ | S77: √ | T77: √ | U77: √ | V77: √ | W77: √ | X77: √ | Y77: √ | AB77: √ | AD77: 是 | AE77: 1 | AF77: - | AG77: 已有签字
A78: =ROW()-3 -> 75 | B78: 601 | C78: 06项目验收 | D78: 01项目管理类 | E78: 验收申请单 | F78: 验收申请单 | G78: Word | H78: √ | I78: √ | J78: √ | M78: =_xlfn.TEXTJOIN("_",1,"SPIC_JTTG_XXXX_XXXX",D78,B78&F78,"V1.0_20260106") -> SPIC_JTTG_XXXX_XXXX_01项目管理类_601验收申请单_V1.0_20260106 | N78: 项目群管理支撑 | O78: √ | P78: √ | Q78: √ | R78: √ | S78: √ | T78: √ | U78: √ | V78: √ | W78: √ | X78: √ | Y78: √ | AB78: √ | AD78: 是 | AE78: 1 | AF78: - | AG78: 已有签字
A79: =ROW()-3 -> 76 | B79: 602 | C79: 06项目验收 | D79: 01项目管理类 | E79: 系统试运行报告 | F79: 系统试运行报告 | G79: Word | H79: √ | I79: √ | J79: √ | M79: =_xlfn.TEXTJOIN("_",1,"SPIC_JTTG_XXXX_XXXX",D79,B79&F79,"V1.0_20260106") -> SPIC_JTTG_XXXX_XXXX_01项目管理类_602系统试运行报告_V1.0_20260106 | O79: √ | P79: √ | Q79: √ | R79: √ | S79: √ | T79: √ | U79: √ | V79: √ | W79: √ | X79: √ | Y79: √ | AD79: 是 | AE79: 1 | AF79: - | AG79: 已有签字
A80: =ROW()-3 -> 77 | B80: 603 | C80: 06项目验收 | D80: 01项目管理类 | E80: 遗留问题整改报告（签字版） | F80: 遗留问题整改报告（签字版） | G80: Word | H80: √ | I80: √ | J80: √ | M80: =_xlfn.TEXTJOIN("_",1,"SPIC_JTTG_XXXX_XXXX",D80,B80&F80,"V1.0_20260106") -> SPIC_JTTG_XXXX_XXXX_01项目管理类_603遗留问题整改报告（签字版）_V1.0_20260106 | O80: √ | P80: √ | Q80: √ | R80: √ | S80: √ | T80: √ | U80: √ | V80: √ | W80: √ | X80: √ | Y80: √ | AD80: 是 | AE80: 1 | AF80: - | AG80: 已有签字
A81: =ROW()-3 -> 78 | B81: 604 | C81: 06项目验收 | D81: 01项目管理类 | E81: 验收汇报材料 | F81: 验收汇报材料 | G81: PPT | H81: √ | I81: √ | J81: √ | M81: =_xlfn.TEXTJOIN("_",1,"SPIC_JTTG_XXXX_XXXX",D81,B81&F81,"V1.0_20260106") -> SPIC_JTTG_XXXX_XXXX_01项目管理类_604验收汇报材料_V1.0_20260106 | O81: × | P81: × | Q81: × | R81: × | S81: × | T81: × | U81: × | V81: × | W81: × | X81: × | Y81: × | Z81: × | AA81: × | AD81: 是 | AE81: 1 | AF81: 必需
A82: =ROW()-3 -> 79 | B82: 605 | C82: 06项目验收 | D82: 01项目管理类 | E82: 服务转移确认单 | F82: 服务转移确认单 | G82: Word | H82: √ | I82: √ | J82: √ | M82: =_xlfn.TEXTJOIN("_",1,"SPIC_JTTG_XXXX_XXXX",D82,B82&F82,"V1.0_20260106") -> SPIC_JTTG_XXXX_XXXX_01项目管理类_605服务转移确认单_V1.0_20260106 | O82: √ | P82: √ | Q82: √ | R82: √ | S82: √ | T82: √ | U82: √ | V82: √ | W82: √ | X82: √ | Y82: √ | Z82: √ | AA82: √ | AD82: 是 | AE82: 1 | AF82: - | AG82: 已有签字
A83: =ROW()-3 -> 80 | B83: 000 | C83: 00项目管理 | D83: 01项目管理类 | E83: 项目章程 | F83: 项目章程 | G83: Word | H83: √ | I83: √ | J83: √ | M83: =_xlfn.TEXTJOIN("_",1,"SPIC_JTTG_XXXX_XXXX",D83,B83&F83,"V1.0_20260106") -> SPIC_JTTG_XXXX_XXXX_01项目管理类_000项目章程_V1.0_20260106 | N83: 项目群管理支撑 | O83: × | P83: × | Q83: × | R83: × | S83: × | T83: × | U83: × | V83: × | W83: × | X83: × | Y83: × | Z83: × | AA83: × | AB83: √ | AD83: 否 | AE83: 0
A84: =ROW()-3 -> 81 | B84: 001 | C84: 00项目管理 | D84: 01项目管理类 | E84: 双周滚动计划 | F84: 双周滚动计划 | G84: Excel | H84: √ | I84: √ | J84: √ | M84: =_xlfn.TEXTJOIN("_",1,"SPIC_JTTG_XXXX_XXXX",D84,B84&F84,"V1.0_20260106") -> SPIC_JTTG_XXXX_XXXX_01项目管理类_001双周滚动计划_V1.0_20260106 | N84: 项目群管理支撑 | O84: √ | P84: √ | Q84: √ | R84: √ | S84: √ | T84: √ | U84: √ | V84: √ | W84: √ | X84: √ | Y84: √ | Z84: √ | AA84: √ | AB84: √ | AD84: 是 | AE84: 1
A85: =ROW()-3 -> 82 | B85: 002 | C85: 00项目管理 | D85: 01项目管理类 | E85: 顾问分工表 | F85: 顾问分工表 | G85: Excel | H85: √ | I85: √ | J85: √ | K85: 不涉及 | L85: 不涉及 | M85: =_xlfn.TEXTJOIN("_",1,"SPIC_JTTG_XXXX_XXXX",D85,B85&F85,"V1.0_20260106") -> SPIC_JTTG_XXXX_XXXX_01项目管理类_002顾问分工表_V1.0_20260106 | N85: 项目群管理支撑 | O85: √ | P85: √ | Q85: √ | R85: √ | S85: √ | T85: √ | U85: √ | V85: √ | W85: √ | X85: √ | Y85: √ | Z85: √ | AA85: √ | AB85: √ | AD85: 是 | AE85: 1
A86: =ROW()-3 -> 83 | B86: 003 | C86: 00项目管理 | D86: 01项目管理类 | E86: 关键用户分工表 | F86: 关键用户分工表 | G86: Excel | H86: √ | I86: √ | J86: √ | K86: 不涉及 | L86: 不涉及 | M86: =_xlfn.TEXTJOIN("_",1,"SPIC_JTTG_XXXX_XXXX",D86,B86&F86,"V1.0_20260106") -> SPIC_JTTG_XXXX_XXXX_01项目管理类_003关键用户分工表_V1.0_20260106 | O86: √ | P86: √ | Q86: √ | R86: √ | S86: √ | T86: √ | U86: √ | V86: √ | W86: √ | X86: √ | Y86: √ | Z86: √ | AA86: √ | AB86: × | AD86: 是 | AE86: 1
A87: =ROW()-3 -> 84 | B87: 004 | C87: 00项目管理 | D87: 01项目管理类 | E87: 签到表 | F87: 签到表 | G87: Word | H87: √ | I87: √ | J87: √ | K87: 不涉及 | L87: 不涉及 | M87: =_xlfn.TEXTJOIN("_",1,"SPIC_JTTG_XXXX_XXXX",D87,B87&F87,"V1.0_20260106") -> SPIC_JTTG_XXXX_XXXX_01项目管理类_004签到表_V1.0_20260106 | N87: 项目群管理支撑 | O87: √ | P87: √ | Q87: √ | R87: √ | S87: √ | T87: √ | U87: √ | V87: √ | W87: √ | X87: √ | Y87: √ | Z87: √ | AA87: √ | AB87: √ | AD87: 是 | AE87: 1
A88: =ROW()-3 -> 85 | B88: 005 | C88: 00项目管理 | D88: 01项目管理类 | E88: 会议纪要 | F88: 会议纪要 | G88: Word | H88: √ | I88: √ | J88: √ | K88: 不涉及 | L88: 不涉及 | M88: =_xlfn.TEXTJOIN("_",1,"SPIC_JTTG_XXXX_XXXX",D88,B88&F88,"V1.0_20260106") -> SPIC_JTTG_XXXX_XXXX_01项目管理类_005会议纪要_V1.0_20260106 | N88: / | O88: √ | P88: √ | Q88: √ | R88: √ | S88: √ | T88: √ | U88: √ | V88: √ | W88: √ | X88: √ | Y88: √ | Z88: √ | AA88: √ | AB88: × | AD88: 是 | AE88: 1
A89: =ROW()-3 -> 86 | B89: 006 | C89: 00项目管理 | D89: 01项目管理类 | E89: 会议通知 | F89: 会议通知 | G89: Word | H89: √ | I89: √ | J89: √ | M89: =_xlfn.TEXTJOIN("_",1,"SPIC_JTTG_XXXX_XXXX",D89,B89&F89,"V1.0_20260106") -> SPIC_JTTG_XXXX_XXXX_01项目管理类_006会议通知_V1.0_20260106 | N89: 项目群管理支撑 | O89: √ | P89: √ | Q89: √ | R89: √ | S89: √ | T89: √ | U89: √ | V89: √ | W89: √ | X89: √ | Y89: √ | Z89: √ | AA89: √ | AB89: √ | AD89: 是 | AE89: 1
A90: =ROW()-3 -> 87 | B90: 007 | C90: 00项目管理 | D90: 03技术管理类 | E90: 数据字典 | F90: 数据字典 | G90: Word | H90: √ | M90: =_xlfn.TEXTJOIN("_",1,"SPIC_JTTG_XXXX_XXXX",D90,B90&F90,"V1.0_20260106") -> SPIC_JTTG_XXXX_XXXX_03技术管理类_007数据字典_V1.0_20260106 | O90: √ | P90: √ | Q90: √ | R90: √ | S90: √ | T90: √ | U90: √ | V90: √ | W90: √ | X90: √ | Y90: √ | Z90: √ | AA90: √ | AD90: 否 | AE90: 0
A91: =ROW()-3 -> 88 | B91: 008 | C91: 00项目管理 | D91: 01项目管理类 | E91: 周例会材料 | F91: 周例会材料 | G91: PPT | H91: √ | I91: √ | J91: √ | M91: =_xlfn.TEXTJOIN("_",1,"SPIC_JTTG_XXXX_XXXX",D91,B91&F91,"V1.0_20260106") -> SPIC_JTTG_XXXX_XXXX_01项目管理类_008周例会材料_V1.0_20260106 | N91: 项目群管理支撑 | O91: √ | P91: √ | Q91: √ | R91: √ | S91: √ | T91: √ | U91: √ | V91: √ | W91: √ | X91: √ | Y91: √ | Z91: √ | AA91: √ | AB91: √ | AD91: 是 | AE91: 1
A92: =ROW()-3 -> 89 | B92: 009 | C92: 00项目管理 | D92: 01项目管理类 | E92: 月度例会材料 | F92: 月度例会材料 | G92: PPT | H92: √ | I92: √ | J92: √ | M92: =_xlfn.TEXTJOIN("_",1,"SPIC_JTTG_XXXX_XXXX",D92,B92&F92,"V1.0_20260106") -> SPIC_JTTG_XXXX_XXXX_01项目管理类_009月度例会材料_V1.0_20260106 | N92: 项目群管理支撑 | O92: √ | P92: √ | Q92: √ | R92: √ | S92: √ | T92: √ | U92: √ | V92: √ | W92: √ | X92: √ | Y92: √ | Z92: √ | AA92: √ | AB92: √ | AD92: 是 | AE92: 1
A93: =ROW()-3 -> 90 | B93: 010 | C93: 00项目管理 | D93: 01项目管理类 | E93: 专题汇报材料 | F93: 专题汇报材料 | G93: PPT | H93: √ | I93: √ | J93: √ | M93: =_xlfn.TEXTJOIN("_",1,"SPIC_JTTG_XXXX_XXXX",D93,B93&F93,"V1.0_20260106") -> SPIC_JTTG_XXXX_XXXX_01项目管理类_010专题汇报材料_V1.0_20260106 | N93: 项目群管理支撑 | O93: √ | P93: √ | Q93: √ | R93: √ | S93: √ | T93: √ | U93: √ | V93: √ | W93: √ | X93: √ | Y93: √ | Z93: √ | AA93: √ | AB93: √ | AD93: 是 | AE93: 1
A94: =ROW()-3 -> 91 | B94: 011 | C94: 00项目管理 | D94: 01项目管理类 | E94: 信息安全责任书 | F94: 信息安全责任书 | G94: Word | H94: √ | I94: √ | J94: √ | M94: =_xlfn.TEXTJOIN("_",1,"SPIC_JTTG_XXXX_XXXX",D94,B94&F94,"V1.0_20260106") -> SPIC_JTTG_XXXX_XXXX_01项目管理类_011信息安全责任书_V1.0_20260106 | N94: 项目群管理支撑 | O94: √ | P94: √ | Q94: √ | R94: √ | S94: √ | T94: √ | U94: √ | V94: √ | W94: √ | X94: √ | Y94: √ | Z94: √ | AA94: √ | AB94: √ | AD94: 是 | AE94: 1
A95: =ROW()-3 -> 92 | B95: 012 | C95: 00项目管理 | D95: 01项目管理类 | E95: 项目保密协议 | F95: 项目保密协议 | G95: Word | H95: √ | I95: √ | J95: √ | M95: =_xlfn.TEXTJOIN("_",1,"SPIC_JTTG_XXXX_XXXX",D95,B95&F95,"V1.0_20260106") -> SPIC_JTTG_XXXX_XXXX_01项目管理类_012项目保密协议_V1.0_20260106 | N95: 项目群管理支撑 | O95: √ | P95: √ | Q95: √ | R95: √ | S95: √ | T95: √ | U95: √ | V95: √ | W95: √ | X95: √ | Y95: √ | Z95: √ | AA95: √ | AB95: √ | AD95: 是 | AE95: 1
A96: =ROW()-3 -> 93 | B96: 013 | C96: 00项目管理 | D96: 01项目管理类 | E96: 文档管理办法 | F96: 文档管理办法 | G96: Word | H96: √ | M96: =_xlfn.TEXTJOIN("_",1,"SPIC_JTTG_XXXX_XXXX",D96,B96&F96,"V1.0_20260106") -> SPIC_JTTG_XXXX_XXXX_01项目管理类_013文档管理办法_V1.0_20260106 | N96: 项目群管理支撑 | O96: × | P96: × | Q96: × | R96: × | S96: × | T96: × | U96: × | V96: × | W96: × | X96: × | Y96: × | Z96: × | AA96: × | AB96: √ | AD96: 否 | AE96: 0
A97: =ROW()-3 -> 94 | B97: 014 | C97: 00项目管理 | D97: 01项目管理类 | E97: 项目问题及风险管理办法 | F97: 项目问题及风险管理办法 | G97: Word | H97: √ | M97: =_xlfn.TEXTJOIN("_",1,"SPIC_JTTG_XXXX_XXXX",D97,B97&F97,"V1.0_20260106") -> SPIC_JTTG_XXXX_XXXX_01项目管理类_014项目问题及风险管理办法_V1.0_20260106 | N97: 项目群管理支撑 | O97: × | P97: × | Q97: × | R97: × | S97: × | T97: × | U97: × | V97: × | W97: × | X97: × | Y97: × | Z97: × | AA97: × | AB97: √ | AD97: 否 | AE97: 0
A98: =ROW()-3 -> 95 | B98: 015 | C98: 00项目管理 | D98: 03技术管理类 | E98: 技术开发管控办法 | F98: 技术开发管控办法 | G98: Word | H98: √ | M98: =_xlfn.TEXTJOIN("_",1,"SPIC_JTTG_XXXX_XXXX",D98,B98&F98,"V1.0_20260106") -> SPIC_JTTG_XXXX_XXXX_03技术管理类_015技术开发管控办法_V1.0_20260106 | N98: 项目群管理支撑 | O98: × | P98: × | Q98: × | R98: × | S98: × | T98: × | U98: × | V98: × | W98: × | X98: × | Y98: × | Z98: √ | AA98: × | AB98: √ | AD98: 否 | AE98: 1
A99: =ROW()-3 -> 96 | B99: 016 | C99: 00项目管理 | D99: 01项目管理类 | E99: 交付质量管理办法 | F99: 交付质量管理办法 | G99: Word | H99: √ | M99: =_xlfn.TEXTJOIN("_",1,"SPIC_JTTG_XXXX_XXXX",D99,B99&F99,"V1.0_20260106") -> SPIC_JTTG_XXXX_XXXX_01项目管理类_016交付质量管理办法_V1.0_20260106 | N99: 项目群管理支撑 | O99: × | P99: × | Q99: × | R99: × | S99: × | T99: × | U99: × | V99: × | W99: × | X99: × | Y99: × | Z99: × | AA99: × | AB99: √ | AD99: 否 | AE99: 0
A100: =ROW()-3 -> 97 | B100: 017 | C100: 00项目管理 | D100: 01项目管理类 | E100: 沟通机制 | F100: 沟通机制 | G100: Word | H100: √ | M100: =_xlfn.TEXTJOIN("_",1,"SPIC_JTTG_XXXX_XXXX",D100,B100&F100,"V1.0_20260106") -> SPIC_JTTG_XXXX_XXXX_01项目管理类_017沟通机制_V1.0_20260106 | N100: 项目群管理支撑 | O100: × | P100: × | Q100: × | R100: × | S100: × | T100: × | U100: × | V100: × | W100: × | X100: × | Y100: × | Z100: × | AA100: × | AB100: √ | AD100: 是 | AE100: 1
...

Sheet 释义备注
B1: 项目阶段 | C1: 释义 | E1: 文档类型 | F1: 释义 | H1: 文档颗粒度 | J1: 释义
B2: 01 项目准备 | C2: 业主单位与实施厂商快速组建项目实施团队，建章立制，召开项目启动会议，推进项目建设。 | E2: 01项目管理类 | F2: 会议纪要、项目计划、项目章程、项目周报、项目周报、项目月报、项目通知、项目公告、问题清单、项目后勤、新闻手册、组织架构、通类讯录、开账申请、系统运行报告、总结报告、其他 | H2: 共性 | I2: 集团共性 | J2: 面向集团所有单位的统一要求，是保障集团管控、数据标准和业务协同的基础，与集团战略规划匹配。 | K2: 为平衡集团公司 “统一集中管控” 与 “各下属单位业务差异化” 的核心矛盾，规范集团信息化项目需求管理流程，确保需求精准对接集团战略导向、板块业务特性及二级单位实际应用场景，现对需求进行分层分类管理，划分为集团共性需求、板块共性需求、单位个性需求三类
B3: 02 蓝图及详细方案迭代 | C3: 继承已有建设成果，与推广单位进行深度沟通，开展蓝图及详设方案迭代，快速形成集团最优管理模式。 | E3: 02系统实施类 | F3: 现状调研、现状分析报告、业务标准、蓝图方案、专项方案、业务流程、差异分析、单元测试、集成测试、用户接受测试、回归测试、切换策略、上线方案 | I3: 板块共性 | J3: 集团下属同一业务板块（如工程板块、核电板块）内各单位的共同需求，是对集团共性需求的补充和细化。
B4: 03 系统实现 | C4: 按照业务蓝图及详设方案进行系统配置、系统功能开发、单元测试、集成测试，保持业务功能实现与业务蓝图及详设方案一致。 | E4: 03技术管理类 | F4: 开发清单、配置清单、功能说明、接口映射、开发规范、接口集成规范、应用界面字段命名规范 | H4: 个性 | J4: 二级单位特有的、非标准化的需求。源于该单位地域政策、特殊管理模式或历史业务习惯。
B5: 04 上线准备及切换 | C5: 组织用户接受测试，完成系统验证。开展数据收集、系统培训，做好系统上线准备。 | E5: 04数据管理类 | F5: 数据模板、数据标准
B6: 05 上线试运行支持 | C6: 做好系统上线及运维支持工作。 | E6: 05人员培训类 | F6: 培训手册、培训评估、培训计划、培训问卷、操作手册、培训讲义
B7: 06 项目验收 | C7: 具备阶段验收条件，申请项目验收。
B8: 00 项目管理 | C8: 应该包含 项目管理中制度类文档、管理类文档、 项目管理过程需归档文档
B10: 文档命名规则
B11: 模块 | C11: ZTZ-总体组、 FICO-财务、 MM-物资组、 PS-项目组、 PM-设备组、 PP-制造组 、SD-销售组 HR-人资组、BPC-BPC、 BX-报销报账 、SSF-共享运营、 WM-智能仓储 、CM-合同组、 BPM-BPM组 GRC-GRC组、 MDG-MDG组、 INT-集成组、 DAT-数据组 、TEC-技术组 、PMO-项目群组
B12: 版本 | C12: 初始版本为 V0.1，定稿后修改为V1.0，修订后递增（如 V1.1），正式提交版标注 “VF（正式版）
B13: 示例

Sheet 交付管理
B1: 意义要达到的效果、适用程度、以及编号分配周期
A2: 序号 | B2: 交付物编号 | C2: 文档命名规则 | D2: 项目阶段 | E2: 责任方 | F2: 文档分类 | G2: 文档 | H2: 文档类型 | I2: 适用范围 | J2: 涉及系统/模块 | K2: 迭代周期 | L2: 检查点 | M2: 合同规定（Y/N） | N2: 访问权限 | O2: 备注 | P2: 注意事项：专业系统、基础组件、集成技术、basis视角需要补充讨论
A3: 1 | D3: 项目管理 | E3: 集团PMO | F3: 汇报文档 | G3: 周例会材料 | H3: PPT | K3: 不迭代 | N3: 内部
A4: 2 | D4: 项目管理 | E4: 集团PMO | F4: 汇报文档 | G4: 月度例会材料 | H4: PPT | K4: 不迭代 | N4: 内部
A5: 3 | D5: 项目管理 | E5: 集团PMO | F5: 汇报文档 | G5: 专题汇报 | H5: PPT | K5: 不迭代 | N5: 内部
A6: 4 | D6: 项目管理 | E6: 集团PMO | F6: 汇报文档 | G6: 专项汇报 | H6: PPT | K6: 不迭代 | N6: 内部
A7: 5 | D7: 项目管理 | E7: 集团PMO | F7: 会议管理 | G7: PMO会议纪要 | H7: Word | K7: 不迭代 | L7: 签字 | N7: 内部
A8: 6 | D8: 项目管理 | E8: ？ | F8: 规章制度 | G8: 信息安全责任书 | H8: Word | N8: 公开
A9: 7 | D9: 项目管理 | E9: ？ | F9: 规章制度 | G9: 项目保密协议 | H9: Word | N9: 公开
A10: 8 | D10: 项目管理 | E10: ？ | F10: 规章制度 | G10: 文档命名规范 | H10: Word | N10: 公开
A11: 9 | D11: 项目管理 | E11: ？ | F11: 规章制度 | G11: 项目交付清单 | H11: Word | N11: 公开
A12: 10 | D12: 项目管理 | E12: ？ | F12: 规章制度 | G12: 文档模板 | H12: Word/Excel | N12: 公开
A13: 11 | D13: 项目管理 | E13: ？ | F13: 规章制度 | G13: 文档服务器管理 | H13: PDF | N13: 公开
A14: 12 | D14: 项目管理 | E14: ？ | F14: 规章制度 | G14: 项目问题及风险管理办法 | H14: Word | N14: 公开
A15: 13 | D15: 项目管理 | E15: ？ | F15: 规章制度 | G15: 技术开发管控办法 | H15: Word | N15: 公开
A16: 14 | D16: 项目管理 | E16: ？ | F16: 规章制度 | G16: 交付质量管理 | H16: Word | N16: 公开
A17: 15 | D17: 项目管理 | E17: ？ | F17: 规章制度 | G17: 沟通机制 | H17: Word | N17: 公开
A18: 16 | D18: 项目管理 | E18: ？ | F18: 规章制度 | G18: 进度管理机制 | H18: Word | N18: 公开
A19: 17 | D19: 项目管理 | E19: ？ | F19: 规章制度 | G19: 项目变更管理办法 | H19: Word | N19: 公开
... A28: 26 | D28: 项目管理 | E28: 厂商PMO | F28: 过程管理 | G28: 项目模板 | H28: Excel/Word/PPT | N28: 公开
A29: 27 | D29: 项目管理 | E29: 厂商PMO | F29: 过程管理 | G29: 上线申请报告 | H29: Word | K29: 不迭代 | L29: 签字 | N29: 公开
A30: 28 | D30: 项目管理 | E30: 厂商PMO | F30: 过程管理 | G30: 开账申请 | H30: Word | K30: 不迭代 | L30: 签字 | N30: 公开
A31: 29 | D31: 项目管理 | E31: 厂商PMO | F31: 问题管理 | G31: 详设阶段问题清单 | H31: Excel | J31: ERP | K31: 阶段内迭代 | N31: 公开
A32: 30 | D32: 项目管理 | E32: 厂商PMO | F32: 问题管理 | G32: 单元测试问题清单 | H32: Excel | J32: ERP | K32: 阶段内迭代 | N32: 公开
A33: 31 | D33: 项目管理 | E33: 厂商PMO | F33: 问题管理 | G33: 集成测试问题清单 | H33: Excel | J33: ERP | K33: 阶段内迭代 | N33: 公开
A34: 32 | D34: 项目管理 | E34: 厂商PMO | F34: 问题管理 | G34: UAT测试问题清单 | H34: Excel | J34: ERP | K34: 阶段内迭代 | N34: 公开
A35: 33 | D35: 项目管理 | E35: 厂商PMO | F35: 问题管理 | G35: 上线切换问题清单 | H35: Excel | J35: ERP | K35: 阶段内迭代 | N35: 公开
A36: 34 | D36: 项目管理 | E36: 厂商PMO | F36: 问题管理 | G36: 试运行问题清单 | H36: Excel | J36: ERP | K36: 阶段内迭代 | N36: 公开
A37: 35 | D37: 项目管理 | E37: 厂商PMO | F37: 问题管理 | G37: 建转运问题清单 | H37: Excel | J37: ERP | K37: 阶段内迭代 | N37: 公开
A38: 36 | D38: 项目管理 | E38: 厂商PMO | F38: 需求管理 | G38: 需求申请单 | H38: Word | J38: ERP | K38: 不迭代 | L38: 签字 | N38: 公开
A39: 37 | D39: 项目管理 | E39: 厂商PMO | F39: 需求管理 | G39: 需求评审记录 | H39: Excel/Word | J39: ERP | K39: 阶段迭代 | N39: 公开
A40: 38 | D40: 项目管理 | E40: 厂商PMO | F40: 需求管理 | G40: 评审材料 | H40: PPT | J40: ERP | K40: 不迭代 | N40: 公开
A41: 39 | D41: 项目管理 | E41: 厂商PMO | F41: 需求管理 | G41: 评审会议纪要 | H41: Word | J41: ERP | K41: 不迭代 | L41: 签字 | N41: 公开
A42: 40 | D42: 项目准备 | E42: 各实施厂商 | F42: 进度管理 | G42: 项目进度计划 | H42: Excel | N42: 公开
A43: 41 | D43: 项目准备 | E43: 各实施厂商 | F43: 资源管理 | G43: 通讯录 | H43: Excel | N43: 公开
A44: 42 | D44: 项目准备 | E44: 各实施厂商 | F44: 资源管理 | G44: 顾问分工表 | H44: Excel | N44: 公开
A45: 43 | D45: 项目准备 | E45: 各实施厂商 | F45: 资源管理 | G45: 关键用户分工表 | H45: Excel | N45: 公开
A46: 44 | D46: 项目准备 | E46: 各实施厂商 | F46: 培训管理 | G46: 培训材料 | H46: Excel/Word/PPT | N46: 公开
A47: 45 | D47: 项目准备 | E47: 各实施厂商 | F47: 培训管理 | G47: 培训录屏 | H47: Mp4 | N47: 公开
A48: 46 | D48: 项目准备 | E48: 各实施厂商 | F48: 培训管理 | G48: 签到表 | H48: Word | N48: 公开
A49: 47 | D49: 项目准备 | E49: 各实施厂商 | F49: 过程管理 | G49: 会议纪要？ | H49: Word | N49: 公开
D50: 详细设计 | G50: 需求清单 | H50: Excel | N50: 公开
A51: 48 | D51: 详细设计 | G51: 差异分析报告 | H51: Word | N51: 公开
A52: 49 | D52: 详细设计 | G52: 业务标准？ | H52: Word | N52: 公开
A53: 50 | D53: 详细设计 | G53: 流程清单 | H53: Excel | N53: 公开
A54: 51 | D54: 详细设计 | G54: 专题方案 | H54: PPT | N54: 公开
G55: 蓝图 | H55: PPT | I55: 总体组、推广单位（二级单位） | N55: 公开
A56: 52 | D56: 详细设计 | G56: 详细设计方案 | H56: PPT | I56: 总体组 | N56: 公开
A57: 53 | D57: 详细设计 | G57: 详细设计方案 | H57: Word | N57: 公开 | O57: 含业务流程、专题方案
A58: 56 | D58: 详细设计 | G58: 详细设计方案（评审汇报材料） | H58: PPT | K58: 不迭代 | L58: 签字 | N58: 公开
A59: 54 | D59: 详细设计 | G59: 会议通知 | H59: Word | K59: 不迭代 | L59: 签字 | N59: 公开
A60: 55 | D60: 详细设计 | G60: 评审手册 | H60: Word | K60: 不迭代 | L60: 签字 | N60: 公开
A61: 57 | D61: 详细设计 | G61: 签到表 | H61: Word | K61: 不迭代 | L61: 签字 | N61: 公开
A62: 58 | D62: 详细设计 | G62: 评审意见单 | H62: Word | K62: 不迭代 | L62: 签字 | N62: 公开
A63: 59 | D63: 系统实现 | E63: 各实施厂商 | F63: 业务文档 | G63: 模块权限角色清单 | H63: Excel | N63: 公开
A64: 60 | D64: 系统实现 | E64: 各实施厂商 | F64: 业务文档 | G64: 系统配置清单 | H64: Excel | N64: 公开
A65: 61 | D65: 系统实现 | E65: 各实施厂商 | F65: 业务文档 | G65: 开发说明书 | H65: Word | N65: 公开
A66: 62 | D66: 系统实现 | E66: 各实施厂商 | F66: 业务文档 | G66: 数据字典 | H66: Excel | N66: 公开
A67: 63 | D67: 系统实现 | E67: 各实施厂商 | F67: 技术文档 | G67: 技术说明书 | H67: Word | N67: 公开
A68: 64 | D68: 测试阶段 | E68: 各实施厂商 | F68: 单元测试 | G68: 单元测试场景清单 | H68: Excel | N68: 公开
A69: 65 | D69: 测试阶段 | E69: 各实施厂商 | F69: 单元测试 | G69: 单元测试脚本 | H69: Excel | N69: 公开
A70: 66 | D70: 测试阶段 | E70: 各实施厂商 | F70: 单元测试 | G70: 单元测试报告（签字版） | H70: Word | N70: 公开
A71: 67 | D71: 测试阶段 | E71: 各实施厂商 | F71: 集成测试 | G71: 集成测试场景清单 | H71: Excel | N71: 公开
A72: 68 | D72: 测试阶段 | E72: 各实施厂商 | F72: 集成测试 | G72: 集成测试脚本 | H72: Excel | N72: 公开
A73: 69 | D73: 测试阶段 | E73: 各实施厂商 | F73: 集成测试 | G73: 集成测试报告（签字版） | H73: Word | N73: 公开
A74: 70 | D74: 测试阶段 | E74: ？ | F74: 压力测试 | G74: 压力测试报告 | H74: Word | N74: 公开
... A82: 78 | D82: 上线准备 | E82: 各实施厂商 | F82: 过程管理 | G82: 上线切换方案 | H82: Word/PPT | N82: 公开
A83: 79 | D83: 上线准备 | E83: 各实施厂商 | F83: 过程管理 | G83: 系统应急方案 | N83: 公开
A84: 80 | D84: 上线准备 | E84: 各实施厂商 | F84: 过程管理 | G84: 安全检查报告 | N84: 公开
A85: 81 | D85: 上线切换 | E85: 各实施厂商 | F85: 试运行 | G85: 系统试运行期运维方案 | N85: 公开
A86: 82 | D86: 上线切换 | E86: 各实施厂商 | F86: 试运行 | G86: 试运行期间问题清单 | N86: 公开
A87: 83 | D87: 上线切换 | E87: 各实施厂商 | F87: 试运行 | G87: 项目总结报告 | N87: 公开
A88: 84 | D88: 上线切换 | E88: 各实施厂商 | F88: 试运行 | G88: 试运行报告 | N88: 公开
A89: 85 | D89: 上线切换 | E89: 各实施厂商 | F89: 建转运 | G89: 建转运方案 | N89: 公开
A90: 86 | D90: 上线切换 | E90: 各实施厂商 | F90: 建转运 | G90: 建转运交接清单 | N90: 公开
A91: 87 | D91: 上线切换 | E91: 各实施厂商 | F91: 建转运 | G91: 涉及开发的程序/系统源代码 | N91: 公开
A92: 88 | D92: 上线切换 | E92: 各实施厂商 | F92: 建转运 | G92: 建转运问题清单 | N92: 公开
A93: 89 | D93: 项目验收 | E93: 各实施厂商 | F93: 验收文档 | G93: 文档验收报告 | N93: 内部
A94: 90 | D94: 项目验收 | E94: 各实施厂商 | F94: 验收文档 | G94: 验收申请单 | N94: 内部
... A97: 93 | D97: 项目验收 | E97: 各实施厂商 | F97: 验收文档 | G97: 验收汇报材料 | N97: 内部

Sheet 分工
A1: 项目阶段 | B1: 牵头 | C1: 第一版 | D1: 第二版
A2: 01 项目准备 | B2: 罗沿鑫 | C2: 已完成 | D2: 已完成
A3: 02 蓝图及详细方案迭代 | B3: 俞敏 | C3: 已完成 | D3: 已完成
A4: 03 系统实现 | B4: 李红斌 | C4: 已完成 | D4: 已完成
A5: 04 上线准备及切换 | B5: 陈浩 | C5: 已完成 | D5: 已完成
A6: 05 上线试运行支持 | B6: 张冬冬 | C6: 已完成 | D6: 已完成
A7: 06 项目验收 | B7: 李昂 | C7: 已完成 | D7: 已完成
A8: 00 项目管理 | B8: 王兴 | C8: 已完成 | D8: 已完成

Sheet 数据统计表
B3: 序号 | C3: 文档分类 | D3: 交付物清单项 | E3: 已形成初稿 | F3: 初稿编制中 | G3: 不涉及 | H3: 备注
B4: 1 | C4: 项目管理 | D4: =COUNTA(阶段交付物情况!C83:C120) -> 38 | E4: =SUM(阶段交付物情况!AE83:AE120) -> 22 | F4: =COUNTIF(阶段交付物情况!AE83:AE120,"0") -> 14 | G4: =COUNTIF(阶段交付物情况!AE83:AE120,"不涉及") -> 2
B5: 2 | C5: 项目准备 | D5: =COUNTA(阶段交付物情况!C4:C15) -> 12 | E5: =SUM(阶段交付物情况!AE4:AE15) -> 11 | F5: =COUNTIF(阶段交付物情况!AE4:AE15,"0") -> 1 | G5: =COUNTIF(阶段交付物情况!AE4:AE15,"不涉及") -> 0
B6: 3 | C6: 蓝图及详细方案迭代 | D6: =COUNTA(阶段交付物情况!C16:C38) -> 23 | E6: =SUM(阶段交付物情况!AE16:AE38) -> 30 | F6: =COUNTIF(阶段交付物情况!AE16:AE38,"0") -> 0 | G6: =COUNTIF(阶段交付物情况!AE16:AE38,"不涉及") -> 0
B7: 4 | C7: 系统实现 | D7: =COUNTA(阶段交付物情况!C39:C54) -> 16 | E7: =SUM(阶段交付物情况!AE39:AE54) -> 17 | F7: =COUNTIF(阶段交付物情况!AE39:AE54,"0") -> 0 | G7: =COUNTIF(阶段交付物情况!AE39:AE54,"不涉及") -> 1
B8: 5 | C8: 上线准备及切换 | D8: =COUNTA(阶段交付物情况!C55:C72) -> 18 | E8: =SUM(阶段交付物情况!AE55:AE72) -> 26 | F8: =COUNTIF(阶段交付物情况!AE55:AE72,"0") -> 0 | G8: =COUNTIF(阶段交付物情况!AE55:AE72,"不涉及") -> 1
B9: 6 | C9: 上线试运行支持 | D9: =COUNTA(阶段交付物情况!C73:C76) -> 4 | E9: =SUM(阶段交付物情况!AE73:AE76) -> 4 | F9: =COUNTIF(阶段交付物情况!AE73:AE76,"0") -> 0 | G9: =COUNTIF(阶段交付物情况!AE73:AE76,"不涉及") -> 0
B10: 7 | C10: 项目验收 | D10: =COUNTA(阶段交付物情况!C77:C82) -> 6 | E10: =SUM(阶段交付物情况!AE77:AE82) -> 6 | F10: =COUNTIF(阶段交付物情况!AE77:AE82,"0") -> 0 | G10: =COUNTIF(阶段交付物情况!AE77:AE82,"不涉及") -> 0
B11: 合计 | D11: =SUM(D4:D10) -> 117 | E11: =SUM(E4:E10) -> 116 | F11: =SUM(F4:F10) -> 15 | G11: =SUM(G4:G10) -> 4

Sheet 文档变更记录
A1: 序号 | B1: 调整分类 | C1: 调整内容 | D1: 调整依据 | E1: 提出人员 | F1: 日期
A2: =ROW()-1 -> 1
A3: =ROW()-1 -> 2
A4: =ROW()-1 -> 3
A5: =ROW()-1 -> 4
A6: =ROW()-1 -> 5
A7: =ROW()-1 -> 6
A8: =ROW()-1 -> 7
A9: =ROW()-1 -> 8
A10: =ROW()-1 -> 9
A11: =ROW()-1 -> 10
A12: =ROW()-1 -> 11
A13: =ROW()-1 -> 12
... A17: =ROW()-1 -> 16

Sheet 关键文档质量要求（草稿）
A2: 序号 | B2: 交付物 | C2: 质量要求 | D2: 对应交付物文档 | E2: 备注
A3: =ROW()-2 -> 1 | B3: 《启动会材料》 | C3: 1、包括项目实施目标、实施范围； 2、包括项目组织架构和核心成员； 3、包括项目里程碑计划、沟通汇报计划、风险管理计划； 4、包括项目整体情况介绍； | D3: 101启动会材料
A4: =ROW()-2 -> 2 | B4: 《项目计划》 | C4: 1、项目进度计划包括项目里程碑节点和项目详细计划； 2、项目详细计划中包含项目阶段内的活动，例如单元测试、集成测试、系统联调测试等； 3、包括质量保证活动，例如需求评审、方案评审、测试、验收审查等； | D4: 102项目里程碑计划、103项目详细计划
A5: =ROW()-2 -> 3 | B5: 《需求收集清单》 | C5: 1、业务需求进行了充分分解和详细描述，不遗漏不重复，可度量可实现可交付； 2、对性能、安全、交互性等非业务性需求进行了详细描述，可度量；
A6: =ROW()-2 -> 4 | B6: 《需求跟踪表》 | C6: 1、项目建设过程中用户提出的需求变更和新需求，详细记录和响应状态跟踪； 2、需要关联需求最终状态，如开发状态、生产及发布状态等 3、需明确需求当前状态、处理及跟进情况 | D6: 200总体共性需求清单、206板块共性需求清单、211个性需求清单
A7: =ROW()-2 -> 5 | B7: 《详细设计方案》 | C7: 1、包括系统集成架构、系统业务架构； 2、包括系统业务架构及逻辑架构； 3、包括系统业务模块划分和功能架构； 4、包括核心和重点业务的设计和处理流程； 5、包括权限设计、流程设计等内容； 6、包括数据库结构设计，系统内部各模块间数据集成； 7、包括与外部系统数据和业务集成架构；
A8: =ROW()-2 -> 6 | B8: 《功能说明书》 | C8: 1、关联清晰业务处理逻辑； 2、需要明确清晰的业务逻辑变更记录及时间； 3、包括功能界面设计； 4、包括标题、数据查询、统计、翻页、导入、导出等辅助功能齐全； 5、包括数据存储说明； 6、包括规范的数据输入值（值列表、下拉列表等）描述； | D8: 300共性功能设计说明书、307个性功能设计说明书
A9: =ROW()-2 -> 7 | B9: 《项目方案评审报告》 | C9: 根据评审记录包含评审意见、评审人签字等原始记录 | D9: 219详细设计方案评审汇报材料、220评审意见单、025需求评审材料、026需求评审记录、027评审会议纪要
A10: =ROW()-2 -> 8 | B10: 《需求变更》 | C10: 1、变更原因、内容、功能等详细说明； 2、需要包含需求变更签字确认文件、需求变更评审记录、需求评审会议纪要
A11: =ROW()-2 -> 9 | B11: 《问题跟踪表》 | C11: 1、项目建设过程中用户提出的问题需要按阶段管理 2、问题分类清晰、责任人清晰等需详细记录和响应状态跟踪 3、需要关联问题最终状态，如开发状态、生产及发布状态等 4、需明确问题当前状态、处理及跟进情况
A12: =ROW()-2 -> 10 | B12: 《测试方案》 | C12: 1、分别针对功能测试、集成测试、安全测试、性能测试、用户接收测试编写测试方法、用例、环境、数据准备以及时间计划； 2、包括测试计划、测试方法； 3、包含全部业务需求的测试案例（测试功能点、输入、预期输出）； 4、包含测试范围、涉及的自建或统建系统 | D12: 302总体组单元测试计划及场景、304总体组集成测试计划及场景、309二级单位单元测试计划及场景、311二级单位集成测试计划及场景、404UAT测试计划及场景、414性能测试方案
A13: =ROW()-2 -> 11 | B13: 《测试报告》 | C13: 1、要求开展UAT测试，提供用户接受测试报告（签字）； 2、包括系统功能测试报告（集成测试报告可包含在功能测试报告内）（签字）；测试执行情况及结果、整改措施和确认签字 3、包括性能测试报告（签字）；测试执行情况及结果、整改措施和确认签字 4、包括系统上线安全检测报告（安全漏扫、渗透测试等），测试执行情况及结果、整改措施和确认签字； | D13: 303总体组单元测试报告、305总体组集成测试报告 310二级单位单元测试报告、312二级单位集成测试报告、405UAT测试报告、415性能测试报告
A14: =ROW()-2 -> 12 | B14: 《用户操作手册》 | C14: 1、业务场景覆盖全部业务需求，操作说明清晰易懂，包括回退等异常业务操作的说明； 2、业务操作说明与操作功能界面截图清晰对应； | D14: 411操作手册
A15: =ROW()-2 -> 13 | B15: 《培训方案》、《培训材料》、培训视频 | C15: 1、包含系统功能操作培训、常见问题解决方案，系统方案、集成架构、业务架构等。 | D15: 109关键用户入场培训材料、110实施顾问入场培训材料
A16: =ROW()-2 -> 14 | B16: 《项目建转运方案》 | C16: 1、需包含知识转移方案、知识转移计划。 2、需包含常见问题清单、业务系统方案、相关业务文档 | D16: 032建转运方案
A17: =ROW()-2 -> 15 | B17: 《试运行期运维方案》 | C17: 1、包括试用期运维人员安排和运维职责分工； 2、包括运维操作管理规程，运维工作流程； 3、包括风险隐患排查整改周期、应急预案、应急演练计划； 4、包括应急处置措施； | D17: 030系统试运行期运维方案
A18: =ROW()-2 -> 16 | B18: 《上线申请表》 | C18: 1、上线申请单完成签字； 2、包含各系统配置情况检查、数据、权限等检查 | D18: 409上线开账准备及开账申请
A19: =ROW()-2 -> 17 | B19: 《试运行报告》 | C19: 1、包括对试运行阶段的保障工作进行回顾和总结； 2、包括故障和问题处理情况总结； 3、包括系统试运行效果整体评价； | D19: 602系统试运行报告
A20: =ROW()-2 -> 18 | B20: 《验收申请单》 | C20: 1、申请时先提供word版，待验收流程完成后签字扫描，提供电子版； 2、含合同规定的内容完成情况清单、项目验收提交资料清单、系统遗留问题备忘录 | D20: 601验收申请单
A21: =ROW()-2 -> 19 | B21: 《验收汇报材料》 | C21: 1、包括项目建设过程回顾； 2、包括项目的总体解决方案的概述； 3、包括项目建设目标实现情况、项目亮点总结和经验建议； 4、包括系统遗留问题整改情况； 5、包括系统试运行情况总结； 6、系统后续运维安排； | D21: 604验收汇报材料
A22: =ROW()-2 -> 20 | B22: 《验收报告》 | C22: 1、包括系统遗留问题解决情况。申请时先提供word版，待验收流程完成后签字扫描，提供电子版； 2、含合同规定的内容完成情况清单； 3、项目验收提交资料清单； 4、项目验收遗留问题备忘录 | D22: 600项目文档验收报告
A23: =ROW()-2 -> 21 | B23: 《项目总结报告》 | C23: 1、包括项目建设历程和建设内容； 2、包括项目资金使用情况，项目成本，项目利润； 3、包括系统上线以来的运维情况总结； 4、包括项目建设效果； 5、包括问题教训和经验总结提炼； | D23: 031项目总结报告
A24: =ROW()-2 -> 22
A25: =ROW()-2 -> 23
A26: =ROW()-2 -> 24
A27: =ROW()-2 -> 25
A28: =ROW()-2 -> 26
A29: =ROW()-2 -> 27
A30: =ROW()-2 -> 28
